[
  {
    "Name": "",
    "Discoverer": "YucaFrita",
    "Glyphs": "1002A11117FF",
    "Platform": "ST",
    "Timestamp": 1713640041000
  },
  {
    "Name": "",
    "Discoverer": "YucaFrita",
    "Glyphs": "100AA11117FF",
    "Platform": "ST",
    "Timestamp": 1711196304000
  },
  {
    "Name": "",
    "Discoverer": "YucaFrita",
    "Glyphs": "100AA11117FF",
    "Platform": "ST",
    "Timestamp": 1711196311000
  },
  {
    "Name": "",
    "Discoverer": "YucaFrita",
    "Glyphs": "100AA11117FF",
    "Platform": "ST",
    "Timestamp": 1711196318000
  },
  {
    "Name": "",
    "Discoverer": "YucaFrita",
    "Glyphs": "100AA11117FF",
    "Platform": "ST",
    "Timestamp": 1711196327000
  },
  {
    "Name": "",
    "Discoverer": "YucaFrita",
    "Glyphs": "100AA11117FF",
    "Platform": "ST",
    "Timestamp": 1711196333000
  },
  {
    "Name": "",
    "Discoverer": "YucaFrita",
    "Glyphs": "100AA11117FF",
    "Platform": "ST",
    "Timestamp": 1711196339000
  },
  {
    "Name": "",
    "Discoverer": "Lunivore",
    "Glyphs": "100BA11117FF",
    "Platform": "ST",
    "Timestamp": 1697360634000
  },
  {
    "Name": "",
    "Discoverer": "Lunivore",
    "Glyphs": "100BA11117FF",
    "Platform": "ST",
    "Timestamp": 1697360650000
  },
  {
    "Name": "",
    "Discoverer": "Lunivore",
    "Glyphs": "100BA11117FF",
    "Platform": "ST",
    "Timestamp": 1697360661000
  },
  {
    "Name": "",
    "Discoverer": "Lunivore",
    "Glyphs": "100BA11117FF",
    "Platform": "ST",
    "Timestamp": 1697360691000
  },
  {
    "Name": "",
    "Discoverer": "Lunivore",
    "Glyphs": "100BA11117FF",
    "Platform": "ST",
    "Timestamp": 1697360696000
  },
  {
    "Name": "",
    "Discoverer": "Lunivore",
    "Glyphs": "100BA11117FF",
    "Platform": "ST",
    "Timestamp": 1697360738000
  },
  {
    "Name": "",
    "Discoverer": "Lunivore",
    "Glyphs": "100BA11117FF",
    "Platform": "ST",
    "Timestamp": 1697360757000
  },
  {
    "Name": "",
    "Discoverer": "Lunivore",
    "Glyphs": "100BA11117FF",
    "Platform": "ST",
    "Timestamp": 1697360764000
  },
  {
    "Name": "",
    "Discoverer": "Lunivore",
    "Glyphs": "100BA11117FF",
    "Platform": "ST",
    "Timestamp": 1697360803000
  },
  {
    "Name": "",
    "Discoverer": "Lunivore",
    "Glyphs": "100BA11117FF",
    "Platform": "ST",
    "Timestamp": 1697360809000
  },
  {
    "Name": "",
    "Discoverer": "Lunivore",
    "Glyphs": "100BA11117FF",
    "Platform": "ST",
    "Timestamp": 1697389541000
  },
  {
    "Name": "",
    "Discoverer": "YucaFrita",
    "Glyphs": "100CA11117FF",
    "Platform": "ST",
    "Timestamp": 1713641027000
  },
  {
    "Name": "",
    "Discoverer": "Binder198",
    "Glyphs": "1017A11117FF",
    "Platform": "ST",
    "Timestamp": 1712669306000
  },
  {
    "Name": "",
    "Discoverer": "Binder198",
    "Glyphs": "1024A11117FF",
    "Platform": "ST",
    "Timestamp": 1700313487000
  },
  {
    "Name": "",
    "Discoverer": "YucaFrita",
    "Glyphs": "1027A11117FF",
    "Platform": "ST",
    "Timestamp": 1711289180000
  },
  {
    "Name": "",
    "Discoverer": "YucaFrita",
    "Glyphs": "1027A11117FF",
    "Platform": "ST",
    "Timestamp": 1711289184000
  },
  {
    "Name": "",
    "Discoverer": "YucaFrita",
    "Glyphs": "1027A11117FF",
    "Platform": "ST",
    "Timestamp": 1711289192000
  },
  {
    "Name": "",
    "Discoverer": "YucaFrita",
    "Glyphs": "1027A11117FF",
    "Platform": "ST",
    "Timestamp": 1711289198000
  },
  {
    "Name": "",
    "Discoverer": "YucaFrita",
    "Glyphs": "1027A11117FF",
    "Platform": "ST",
    "Timestamp": 1711289204000
  },
  {
    "Name": "",
    "Discoverer": "YucaFrita",
    "Glyphs": "1027A11117FF",
    "Platform": "ST",
    "Timestamp": 1711289213000
  },
  {
    "Name": "",
    "Discoverer": "YucaFrita",
    "Glyphs": "1027A11117FF",
    "Platform": "ST",
    "Timestamp": 1711289219000
  },
  {
    "Name": "",
    "Discoverer": "YucaFrita",
    "Glyphs": "1027A11117FF",
    "Platform": "ST",
    "Timestamp": 1711289224000
  },
  {
    "Name": "",
    "Discoverer": "YucaFrita",
    "Glyphs": "1027A11117FF",
    "Platform": "ST",
    "Timestamp": 1711289230000
  },
  {
    "Name": "",
    "Discoverer": "YucaFrita",
    "Glyphs": "1027A11117FF",
    "Platform": "ST",
    "Timestamp": 1711289239000
  },
  {
    "Name": "",
    "Discoverer": "YucaFrita",
    "Glyphs": "1027A11117FF",
    "Platform": "ST",
    "Timestamp": 1711289249000
  },
  {
    "Name": "",
    "Discoverer": "YucaFrita",
    "Glyphs": "1027A11117FF",
    "Platform": "ST",
    "Timestamp": 1711289260000
  },
  {
    "Name": "",
    "Discoverer": "YucaFrita",
    "Glyphs": "1027A11117FF",
    "Platform": "ST",
    "Timestamp": 1711289268000
  },
  {
    "Name": "",
    "Discoverer": "LordDraCool241",
    "Glyphs": "103AA11117FF",
    "Platform": "XB",
    "Timestamp": 1712470478000
  },
  {
    "Name": "",
    "Discoverer": "LordDraCool241",
    "Glyphs": "103AA11117FF",
    "Platform": "XB",
    "Timestamp": 1712470485000
  },
  {
    "Name": "",
    "Discoverer": "LordDraCool241",
    "Glyphs": "103AA11117FF",
    "Platform": "XB",
    "Timestamp": 1712470495000
  },
  {
    "Name": "",
    "Discoverer": "LordDraCool241",
    "Glyphs": "103AA11117FF",
    "Platform": "XB",
    "Timestamp": 1712470503000
  },
  {
    "Name": "",
    "Discoverer": "LordDraCool241",
    "Glyphs": "103AA11117FF",
    "Platform": "XB",
    "Timestamp": 1712470513000
  },
  {
    "Name": "",
    "Discoverer": "LordDraCool241",
    "Glyphs": "103AA11117FF",
    "Platform": "XB",
    "Timestamp": 1712470521000
  },
  {
    "Name": "",
    "Discoverer": "Lunivore",
    "Glyphs": "1043A11117FF",
    "Platform": "ST",
    "Timestamp": 1703253095000
  },
  {
    "Name": "",
    "Discoverer": "Lunivore",
    "Glyphs": "1043A11117FF",
    "Platform": "ST",
    "Timestamp": 1703258625000
  },
  {
    "Name": "",
    "Discoverer": "Lunivore",
    "Glyphs": "1052A11117FF",
    "Platform": "ST",
    "Timestamp": 1698842620000
  },
  {
    "Name": "",
    "Discoverer": "Lunivore",
    "Glyphs": "1052A11117FF",
    "Platform": "ST",
    "Timestamp": 1698842638000
  },
  {
    "Name": "",
    "Discoverer": "Lunivore",
    "Glyphs": "1052A11117FF",
    "Platform": "ST",
    "Timestamp": 1698842652000
  },
  {
    "Name": "",
    "Discoverer": "Lunivore",
    "Glyphs": "1052A11117FF",
    "Platform": "ST",
    "Timestamp": 1698842677000
  },
  {
    "Name": "",
    "Discoverer": "Lunivore",
    "Glyphs": "1052A11117FF",
    "Platform": "ST",
    "Timestamp": 1698842696000
  },
  {
    "Name": "",
    "Discoverer": "Lunivore",
    "Glyphs": "1052A11117FF",
    "Platform": "ST",
    "Timestamp": 1698842710000
  },
  {
    "Name": "",
    "Discoverer": "Lunivore",
    "Glyphs": "1052A11117FF",
    "Platform": "ST",
    "Timestamp": 1698842913000
  },
  {
    "Name": "",
    "Discoverer": "Lunivore",
    "Glyphs": "1052A11117FF",
    "Platform": "ST",
    "Timestamp": 1698842923000
  },
  {
    "Name": "",
    "Discoverer": "Lunivore",
    "Glyphs": "1052A11117FF",
    "Platform": "ST",
    "Timestamp": 1698842936000
  },
  {
    "Name": "",
    "Discoverer": "Lunivore",
    "Glyphs": "1052A11117FF",
    "Platform": "ST",
    "Timestamp": 1698842952000
  },
  {
    "Name": "",
    "Discoverer": "Binder198",
    "Glyphs": "1057A11117FF",
    "Platform": "ST",
    "Timestamp": 1711797587000
  },
  {
    "Name": "",
    "Discoverer": "Binder198",
    "Glyphs": "1057A11117FF",
    "Platform": "ST",
    "Timestamp": 1711797629000
  },
  {
    "Name": "",
    "Discoverer": "Binder198",
    "Glyphs": "1059A11117FF",
    "Platform": "ST",
    "Timestamp": 1711797856000
  },
  {
    "Name": "",
    "Discoverer": "Binder198",
    "Glyphs": "1059A11117FF",
    "Platform": "ST",
    "Timestamp": 1711797865000
  },
  {
    "Name": "",
    "Discoverer": "Binder198",
    "Glyphs": "1059A11117FF",
    "Platform": "ST",
    "Timestamp": 1711797872000
  },
  {
    "Name": "",
    "Discoverer": "Binder198",
    "Glyphs": "1059A11117FF",
    "Platform": "ST",
    "Timestamp": 1711797899000
  },
  {
    "Name": "",
    "Discoverer": "Binder198",
    "Glyphs": "1059A11117FF",
    "Platform": "ST",
    "Timestamp": 1712151371000
  },
  {
    "Name": "",
    "Discoverer": "Lunivore",
    "Glyphs": "1062A11117FF",
    "Platform": "ST",
    "Timestamp": 1696855254000
  },
  {
    "Name": "",
    "Discoverer": "Lunivore",
    "Glyphs": "1062A11117FF",
    "Platform": "ST",
    "Timestamp": 1696855292000
  },
  {
    "Name": "",
    "Discoverer": "Lunivore",
    "Glyphs": "1062A11117FF",
    "Platform": "ST",
    "Timestamp": 1696855298000
  },
  {
    "Name": "",
    "Discoverer": "Lunivore",
    "Glyphs": "1062A11117FF",
    "Platform": "ST",
    "Timestamp": 1696856050000
  },
  {
    "Name": "",
    "Discoverer": "Lunivore",
    "Glyphs": "1062A11117FF",
    "Platform": "ST",
    "Timestamp": 1696856060000
  },
  {
    "Name": "",
    "Discoverer": "Lunivore",
    "Glyphs": "1062A11117FF",
    "Platform": "ST",
    "Timestamp": 1696856067000
  },
  {
    "Name": "",
    "Discoverer": "Lunivore",
    "Glyphs": "1062A11117FF",
    "Platform": "ST",
    "Timestamp": 1696856074000
  },
  {
    "Name": "",
    "Discoverer": "Lunivore",
    "Glyphs": "1062A11117FF",
    "Platform": "ST",
    "Timestamp": 1696856120000
  },
  {
    "Name": "",
    "Discoverer": "Binder198",
    "Glyphs": "1066A11117FF",
    "Platform": "ST",
    "Timestamp": 1700090074000
  },
  {
    "Name": "",
    "Discoverer": "Binder198",
    "Glyphs": "1066A11117FF",
    "Platform": "ST",
    "Timestamp": 1700090084000
  },
  {
    "Name": "",
    "Discoverer": "Lunivore",
    "Glyphs": "106CA11117FF",
    "Platform": "ST",
    "Timestamp": 1696324810000
  },
  {
    "Name": "",
    "Discoverer": "Lunivore",
    "Glyphs": "106CA11117FF",
    "Platform": "ST",
    "Timestamp": 1696324819000
  },
  {
    "Name": "",
    "Discoverer": "Lunivore",
    "Glyphs": "106CA11117FF",
    "Platform": "ST",
    "Timestamp": 1696324827000
  },
  {
    "Name": "",
    "Discoverer": "Lunivore",
    "Glyphs": "106CA11117FF",
    "Platform": "ST",
    "Timestamp": 1696324835000
  },
  {
    "Name": "",
    "Discoverer": "Lunivore",
    "Glyphs": "106CA11117FF",
    "Platform": "ST",
    "Timestamp": 1696324844000
  },
  {
    "Name": "",
    "Discoverer": "Lunivore",
    "Glyphs": "106CA11117FF",
    "Platform": "ST",
    "Timestamp": 1696324852000
  },
  {
    "Name": "",
    "Discoverer": "Lunivore",
    "Glyphs": "106CA11117FF",
    "Platform": "ST",
    "Timestamp": 1696324859000
  },
  {
    "Name": "",
    "Discoverer": "Binder198",
    "Glyphs": "1095A11117FF",
    "Platform": "ST",
    "Timestamp": 1700007106000
  },
  {
    "Name": "",
    "Discoverer": "Binder198",
    "Glyphs": "1095A11117FF",
    "Platform": "ST",
    "Timestamp": 1700007112000
  },
  {
    "Name": "",
    "Discoverer": "Binder198",
    "Glyphs": "10C5A11117FF",
    "Platform": "ST",
    "Timestamp": 1700093167000
  },
  {
    "Name": "",
    "Discoverer": "Lunivore",
    "Glyphs": "10CDA11117FF",
    "Platform": "ST",
    "Timestamp": 1697391574000
  },
  {
    "Name": "",
    "Discoverer": "Lunivore",
    "Glyphs": "10CDA11117FF",
    "Platform": "ST",
    "Timestamp": 1697391581000
  },
  {
    "Name": "",
    "Discoverer": "LordDraCool241",
    "Glyphs": "10DFA11117FF",
    "Platform": "XB",
    "Timestamp": 1712526353000
  },
  {
    "Name": "",
    "Discoverer": "Lunivore",
    "Glyphs": "10ECA11117FF",
    "Platform": "ST",
    "Timestamp": 1696858975000
  },
  {
    "Name": "",
    "Discoverer": "Lunivore",
    "Glyphs": "10ECA11117FF",
    "Platform": "ST",
    "Timestamp": 1696858989000
  },
  {
    "Name": "",
    "Discoverer": "Lunivore",
    "Glyphs": "10ECA11117FF",
    "Platform": "ST",
    "Timestamp": 1696859012000
  },
  {
    "Name": "",
    "Discoverer": "Binder198",
    "Glyphs": "1103A11117FF",
    "Platform": "ST",
    "Timestamp": 1708178199000
  },
  {
    "Name": "",
    "Discoverer": "Binder198",
    "Glyphs": "1106A11117FF",
    "Platform": "ST",
    "Timestamp": 1700090174000
  },
  {
    "Name": "",
    "Discoverer": "Binder198",
    "Glyphs": "1107A11117FF",
    "Platform": "ST",
    "Timestamp": 1700090698000
  },
  {
    "Name": "",
    "Discoverer": "Binder198",
    "Glyphs": "1108A11117FF",
    "Platform": "ST",
    "Timestamp": 1700090567000
  },
  {
    "Name": "",
    "Discoverer": "Binder198",
    "Glyphs": "1124A11117FF",
    "Platform": "ST",
    "Timestamp": 1700090404000
  },
  {
    "Name": "",
    "Discoverer": "Binder198",
    "Glyphs": "1124A11117FF",
    "Platform": "ST",
    "Timestamp": 1700090412000
  },
  {
    "Name": "",
    "Discoverer": "Lunivore",
    "Glyphs": "112BA11117FF",
    "Platform": "ST",
    "Timestamp": 1696856889000
  },
  {
    "Name": "",
    "Discoverer": "Lunivore",
    "Glyphs": "112BA11117FF",
    "Platform": "ST",
    "Timestamp": 1696856897000
  },
  {
    "Name": "",
    "Discoverer": "Lunivore",
    "Glyphs": "112BA11117FF",
    "Platform": "ST",
    "Timestamp": 1696856905000
  },
  {
    "Name": "",
    "Discoverer": "Lunivore",
    "Glyphs": "112BA11117FF",
    "Platform": "ST",
    "Timestamp": 1696857152000
  },
  {
    "Name": "",
    "Discoverer": "Lunivore",
    "Glyphs": "112BA11117FF",
    "Platform": "ST",
    "Timestamp": 1696857162000
  },
  {
    "Name": "",
    "Discoverer": "Lunivore",
    "Glyphs": "114FA11117FF",
    "Platform": "ST",
    "Timestamp": 1696181729000
  },
  {
    "Name": "",
    "Discoverer": "Lunivore",
    "Glyphs": "114FA11117FF",
    "Platform": "ST",
    "Timestamp": 1696181768000
  },
  {
    "Name": "",
    "Discoverer": "Lunivore",
    "Glyphs": "114FA11117FF",
    "Platform": "ST",
    "Timestamp": 1696181792000
  },
  {
    "Name": "",
    "Discoverer": "Lunivore",
    "Glyphs": "114FA11117FF",
    "Platform": "ST",
    "Timestamp": 1696181802000
  },
  {
    "Name": "",
    "Discoverer": "Lunivore",
    "Glyphs": "114FA11117FF",
    "Platform": "ST",
    "Timestamp": 1696181814000
  },
  {
    "Name": "",
    "Discoverer": "Lunivore",
    "Glyphs": "114FA11117FF",
    "Platform": "ST",
    "Timestamp": 1696181825000
  },
  {
    "Name": "",
    "Discoverer": "Lunivore",
    "Glyphs": "114FA11117FF",
    "Platform": "ST",
    "Timestamp": 1696181856000
  },
  {
    "Name": "",
    "Discoverer": "Lunivore",
    "Glyphs": "1151A11117FF",
    "Platform": "ST",
    "Timestamp": 1695754918000
  },
  {
    "Name": "",
    "Discoverer": "Lunivore",
    "Glyphs": "1151A11117FF",
    "Platform": "ST",
    "Timestamp": 1695754931000
  },
  {
    "Name": "",
    "Discoverer": "Lunivore",
    "Glyphs": "1151A11117FF",
    "Platform": "ST",
    "Timestamp": 1695754950000
  },
  {
    "Name": "",
    "Discoverer": "Lunivore",
    "Glyphs": "1151A11117FF",
    "Platform": "ST",
    "Timestamp": 1695799628000
  },
  {
    "Name": "",
    "Discoverer": "Lunivore",
    "Glyphs": "1152A11117FF",
    "Platform": "ST",
    "Timestamp": 1708775542000
  },
  {
    "Name": "",
    "Discoverer": "Lunivore",
    "Glyphs": "1152A11117FF",
    "Platform": "ST",
    "Timestamp": 1708775549000
  },
  {
    "Name": "",
    "Discoverer": "Lunivore",
    "Glyphs": "1152A11117FF",
    "Platform": "ST",
    "Timestamp": 1708775581000
  },
  {
    "Name": "",
    "Discoverer": "Lunivore",
    "Glyphs": "1152A11117FF",
    "Platform": "ST",
    "Timestamp": 1708777378000
  },
  {
    "Name": "",
    "Discoverer": "Lunivore",
    "Glyphs": "1152A11117FF",
    "Platform": "ST",
    "Timestamp": 1708777394000
  },
  {
    "Name": "",
    "Discoverer": "Lunivore",
    "Glyphs": "1152A11117FF",
    "Platform": "ST",
    "Timestamp": 1708777427000
  },
  {
    "Name": "",
    "Discoverer": "Binder198",
    "Glyphs": "115FA11117FF",
    "Platform": "ST",
    "Timestamp": 1700007493000
  },
  {
    "Name": "",
    "Discoverer": "Binder198",
    "Glyphs": "116BA11117FF",
    "Platform": "ST",
    "Timestamp": 1712493988000
  },
  {
    "Name": "",
    "Discoverer": "LordDraCool241",
    "Glyphs": "1178A11117FF",
    "Platform": "XB",
    "Timestamp": 1712306217000
  },
  {
    "Name": "",
    "Discoverer": "LordDraCool241",
    "Glyphs": "1178A11117FF",
    "Platform": "XB",
    "Timestamp": 1712306227000
  },
  {
    "Name": "",
    "Discoverer": "LordDraCool241",
    "Glyphs": "1178A11117FF",
    "Platform": "XB",
    "Timestamp": 1712306733000
  },
  {
    "Name": "",
    "Discoverer": "LordDraCool241",
    "Glyphs": "1178A11117FF",
    "Platform": "XB",
    "Timestamp": 1712307305000
  },
  {
    "Name": "",
    "Discoverer": "LordDraCool241",
    "Glyphs": "1178A11117FF",
    "Platform": "XB",
    "Timestamp": 1712307314000
  },
  {
    "Name": "",
    "Discoverer": "LordDraCool241",
    "Glyphs": "1178A11117FF",
    "Platform": "XB",
    "Timestamp": 1712343194000
  },
  {
    "Name": "",
    "Discoverer": "LordDraCool241",
    "Glyphs": "1178A11117FF",
    "Platform": "XB",
    "Timestamp": 1712343200000
  },
  {
    "Name": "",
    "Discoverer": "LordDraCool241",
    "Glyphs": "1178A11117FF",
    "Platform": "XB",
    "Timestamp": 1712343206000
  },
  {
    "Name": "",
    "Discoverer": "LordDraCool241",
    "Glyphs": "1178A11117FF",
    "Platform": "XB",
    "Timestamp": 1712349500000
  },
  {
    "Name": "",
    "Discoverer": "Binder198",
    "Glyphs": "117AA11117FF",
    "Platform": "ST",
    "Timestamp": 1711798326000
  },
  {
    "Name": "",
    "Discoverer": "Binder198",
    "Glyphs": "117AA11117FF",
    "Platform": "ST",
    "Timestamp": 1711798334000
  },
  {
    "Name": "",
    "Discoverer": "Binder198",
    "Glyphs": "117AA11117FF",
    "Platform": "ST",
    "Timestamp": 1711798359000
  },
  {
    "Name": "",
    "Discoverer": "Binder198",
    "Glyphs": "117AA11117FF",
    "Platform": "ST",
    "Timestamp": 1711973140000
  },
  {
    "Name": "",
    "Discoverer": "Binder198",
    "Glyphs": "117DA11117FF",
    "Platform": "ST",
    "Timestamp": 1712151519000
  },
  {
    "Name": "",
    "Discoverer": "Binder198",
    "Glyphs": "117DA11117FF",
    "Platform": "ST",
    "Timestamp": 1712151527000
  },
  {
    "Name": "",
    "Discoverer": "Binder198",
    "Glyphs": "117DA11117FF",
    "Platform": "ST",
    "Timestamp": 1712151536000
  },
  {
    "Name": "",
    "Discoverer": "YucaFrita",
    "Glyphs": "1182A11117FF",
    "Platform": "ST",
    "Timestamp": 1712178035000
  },
  {
    "Name": "",
    "Discoverer": "YucaFrita",
    "Glyphs": "1182A11117FF",
    "Platform": "ST",
    "Timestamp": 1712178041000
  },
  {
    "Name": "",
    "Discoverer": "YucaFrita",
    "Glyphs": "1182A11117FF",
    "Platform": "ST",
    "Timestamp": 1712178047000
  },
  {
    "Name": "",
    "Discoverer": "YucaFrita",
    "Glyphs": "1182A11117FF",
    "Platform": "ST",
    "Timestamp": 1712178055000
  },
  {
    "Name": "",
    "Discoverer": "YucaFrita",
    "Glyphs": "1182A11117FF",
    "Platform": "ST",
    "Timestamp": 1712178064000
  },
  {
    "Name": "",
    "Discoverer": "YucaFrita",
    "Glyphs": "1182A11117FF",
    "Platform": "ST",
    "Timestamp": 1712178153000
  },
  {
    "Name": "",
    "Discoverer": "YucaFrita",
    "Glyphs": "1182A11117FF",
    "Platform": "ST",
    "Timestamp": 1712178161000
  },
  {
    "Name": "",
    "Discoverer": "YucaFrita",
    "Glyphs": "1182A11117FF",
    "Platform": "ST",
    "Timestamp": 1712178171000
  },
  {
    "Name": "",
    "Discoverer": "YucaFrita",
    "Glyphs": "1182A11117FF",
    "Platform": "ST",
    "Timestamp": 1713006397000
  },
  {
    "Name": "",
    "Discoverer": "YucaFrita",
    "Glyphs": "118BA11117FF",
    "Platform": "ST",
    "Timestamp": 1711747512000
  },
  {
    "Name": "",
    "Discoverer": "YucaFrita",
    "Glyphs": "118BA11117FF",
    "Platform": "ST",
    "Timestamp": 1711747587000
  },
  {
    "Name": "",
    "Discoverer": "YucaFrita",
    "Glyphs": "118BA11117FF",
    "Platform": "ST",
    "Timestamp": 1711747639000
  },
  {
    "Name": "",
    "Discoverer": "YucaFrita",
    "Glyphs": "118BA11117FF",
    "Platform": "ST",
    "Timestamp": 1711747673000
  },
  {
    "Name": "",
    "Discoverer": "YucaFrita",
    "Glyphs": "118BA11117FF",
    "Platform": "ST",
    "Timestamp": 1711747695000
  },
  {
    "Name": "",
    "Discoverer": "YucaFrita",
    "Glyphs": "118BA11117FF",
    "Platform": "ST",
    "Timestamp": 1711747717000
  },
  {
    "Name": "",
    "Discoverer": "YucaFrita",
    "Glyphs": "118BA11117FF",
    "Platform": "ST",
    "Timestamp": 1711747731000
  },
  {
    "Name": "",
    "Discoverer": "YucaFrita",
    "Glyphs": "118BA11117FF",
    "Platform": "ST",
    "Timestamp": 1711747821000
  },
  {
    "Name": "",
    "Discoverer": "YucaFrita",
    "Glyphs": "118BA11117FF",
    "Platform": "ST",
    "Timestamp": 1711747858000
  },
  {
    "Name": "",
    "Discoverer": "YucaFrita",
    "Glyphs": "118BA11117FF",
    "Platform": "ST",
    "Timestamp": 1711747872000
  },
  {
    "Name": "",
    "Discoverer": "Gennie",
    "Glyphs": "1197A11117FF",
    "Platform": "ST",
    "Timestamp": 1708365650000
  },
  {
    "Name": "",
    "Discoverer": "YucaFrita",
    "Glyphs": "2001A11117FF",
    "Platform": "ST",
    "Timestamp": 1695935900000
  },
  {
    "Name": "",
    "Discoverer": "YucaFrita",
    "Glyphs": "2001A11117FF",
    "Platform": "ST",
    "Timestamp": 1695935914000
  },
  {
    "Name": "",
    "Discoverer": "YucaFrita",
    "Glyphs": "2001A11117FF",
    "Platform": "ST",
    "Timestamp": 1695935923000
  },
  {
    "Name": "",
    "Discoverer": "YucaFrita",
    "Glyphs": "2001A11117FF",
    "Platform": "ST",
    "Timestamp": 1695935932000
  },
  {
    "Name": "",
    "Discoverer": "YucaFrita",
    "Glyphs": "2001A11117FF",
    "Platform": "ST",
    "Timestamp": 1695935978000
  },
  {
    "Name": "",
    "Discoverer": "Binder198",
    "Glyphs": "200DA11117FF",
    "Platform": "ST",
    "Timestamp": 1712151422000
  },
  {
    "Name": "",
    "Discoverer": "Binder198",
    "Glyphs": "200DA11117FF",
    "Platform": "ST",
    "Timestamp": 1712151432000
  },
  {
    "Name": "",
    "Discoverer": "Binder198",
    "Glyphs": "200DA11117FF",
    "Platform": "ST",
    "Timestamp": 1712151440000
  },
  {
    "Name": "",
    "Discoverer": "Binder198",
    "Glyphs": "200DA11117FF",
    "Platform": "ST",
    "Timestamp": 1712151449000
  },
  {
    "Name": "",
    "Discoverer": "Binder198",
    "Glyphs": "200DA11117FF",
    "Platform": "ST",
    "Timestamp": 1712151468000
  },
  {
    "Name": "",
    "Discoverer": "Lunivore",
    "Glyphs": "2043A11117FF",
    "Platform": "ST",
    "Timestamp": 1703258657000
  },
  {
    "Name": "",
    "Discoverer": "Lunivore",
    "Glyphs": "2043A11117FF",
    "Platform": "ST",
    "Timestamp": 1703258658000
  },
  {
    "Name": "",
    "Discoverer": "Lunivore",
    "Glyphs": "2043A11117FF",
    "Platform": "ST",
    "Timestamp": 1703258659000
  },
  {
    "Name": "",
    "Discoverer": "Lunivore",
    "Glyphs": "2043A11117FF",
    "Platform": "ST",
    "Timestamp": 1703258665000
  },
  {
    "Name": "",
    "Discoverer": "Lunivore",
    "Glyphs": "2052A11117FF",
    "Platform": "ST",
    "Timestamp": 1698863928000
  },
  {
    "Name": "",
    "Discoverer": "Lunivore",
    "Glyphs": "2052A11117FF",
    "Platform": "ST",
    "Timestamp": 1698864013000
  },
  {
    "Name": "",
    "Discoverer": "Lunivore",
    "Glyphs": "2052A11117FF",
    "Platform": "ST",
    "Timestamp": 1698864029000
  },
  {
    "Name": "",
    "Discoverer": "Lunivore",
    "Glyphs": "2052A11117FF",
    "Platform": "ST",
    "Timestamp": 1698864037000
  },
  {
    "Name": "",
    "Discoverer": "Lunivore",
    "Glyphs": "2052A11117FF",
    "Platform": "ST",
    "Timestamp": 1698864043000
  },
  {
    "Name": "",
    "Discoverer": "Lunivore",
    "Glyphs": "2052A11117FF",
    "Platform": "ST",
    "Timestamp": 1698864056000
  },
  {
    "Name": "",
    "Discoverer": "Lunivore",
    "Glyphs": "2052A11117FF",
    "Platform": "ST",
    "Timestamp": 1698864067000
  },
  {
    "Name": "",
    "Discoverer": "Lunivore",
    "Glyphs": "2052A11117FF",
    "Platform": "ST",
    "Timestamp": 1698864072000
  },
  {
    "Name": "",
    "Discoverer": "Lunivore",
    "Glyphs": "2052A11117FF",
    "Platform": "ST",
    "Timestamp": 1698864082000
  },
  {
    "Name": "",
    "Discoverer": "Lunivore",
    "Glyphs": "2052A11117FF",
    "Platform": "ST",
    "Timestamp": 1698864107000
  },
  {
    "Name": "",
    "Discoverer": "Binder198",
    "Glyphs": "2057A11117FF",
    "Platform": "ST",
    "Timestamp": 1709562038000
  },
  {
    "Name": "",
    "Discoverer": "Binder198",
    "Glyphs": "2057A11117FF",
    "Platform": "ST",
    "Timestamp": 1709562055000
  },
  {
    "Name": "",
    "Discoverer": "Binder198",
    "Glyphs": "2059A11117FF",
    "Platform": "ST",
    "Timestamp": 1711797752000
  },
  {
    "Name": "",
    "Discoverer": "Binder198",
    "Glyphs": "2059A11117FF",
    "Platform": "ST",
    "Timestamp": 1711797769000
  },
  {
    "Name": "",
    "Discoverer": "Binder198",
    "Glyphs": "2059A11117FF",
    "Platform": "ST",
    "Timestamp": 1711797777000
  },
  {
    "Name": "",
    "Discoverer": "Binder198",
    "Glyphs": "205AA11117FF",
    "Platform": "ST",
    "Timestamp": 1709512328000
  },
  {
    "Name": "",
    "Discoverer": "Lunivore",
    "Glyphs": "2062A11117FF",
    "Platform": "ST",
    "Timestamp": 1696853251000
  },
  {
    "Name": "",
    "Discoverer": "Lunivore",
    "Glyphs": "2062A11117FF",
    "Platform": "ST",
    "Timestamp": 1696853257000
  },
  {
    "Name": "",
    "Discoverer": "Lunivore",
    "Glyphs": "2062A11117FF",
    "Platform": "ST",
    "Timestamp": 1696853321000
  },
  {
    "Name": "",
    "Discoverer": "Lunivore",
    "Glyphs": "2062A11117FF",
    "Platform": "ST",
    "Timestamp": 1696853343000
  },
  {
    "Name": "",
    "Discoverer": "Lunivore",
    "Glyphs": "2062A11117FF",
    "Platform": "ST",
    "Timestamp": 1696853356000
  },
  {
    "Name": "",
    "Discoverer": "Lunivore",
    "Glyphs": "2062A11117FF",
    "Platform": "ST",
    "Timestamp": 1696853369000
  },
  {
    "Name": "",
    "Discoverer": "Lunivore",
    "Glyphs": "2062A11117FF",
    "Platform": "ST",
    "Timestamp": 1696853387000
  },
  {
    "Name": "",
    "Discoverer": "Lunivore",
    "Glyphs": "2062A11117FF",
    "Platform": "ST",
    "Timestamp": 1696853410000
  },
  {
    "Name": "",
    "Discoverer": "Lunivore",
    "Glyphs": "2062A11117FF",
    "Platform": "ST",
    "Timestamp": 1696853418000
  },
  {
    "Name": "",
    "Discoverer": "Lunivore",
    "Glyphs": "2062A11117FF",
    "Platform": "ST",
    "Timestamp": 1696853423000
  },
  {
    "Name": "",
    "Discoverer": "Lunivore",
    "Glyphs": "2062A11117FF",
    "Platform": "ST",
    "Timestamp": 1696853432000
  },
  {
    "Name": "",
    "Discoverer": "Lunivore",
    "Glyphs": "2062A11117FF",
    "Platform": "ST",
    "Timestamp": 1696853453000
  },
  {
    "Name": "",
    "Discoverer": "Lunivore",
    "Glyphs": "2062A11117FF",
    "Platform": "ST",
    "Timestamp": 1696853460000
  },
  {
    "Name": "",
    "Discoverer": "Lunivore",
    "Glyphs": "2062A11117FF",
    "Platform": "ST",
    "Timestamp": 1696853486000
  },
  {
    "Name": "",
    "Discoverer": "Lunivore",
    "Glyphs": "206CA11117FF",
    "Platform": "ST",
    "Timestamp": 1696324952000
  },
  {
    "Name": "",
    "Discoverer": "Lunivore",
    "Glyphs": "206CA11117FF",
    "Platform": "ST",
    "Timestamp": 1696324959000
  },
  {
    "Name": "",
    "Discoverer": "Lunivore",
    "Glyphs": "206CA11117FF",
    "Platform": "ST",
    "Timestamp": 1696324965000
  },
  {
    "Name": "",
    "Discoverer": "Lunivore",
    "Glyphs": "206CA11117FF",
    "Platform": "ST",
    "Timestamp": 1696324974000
  },
  {
    "Name": "",
    "Discoverer": "Lunivore",
    "Glyphs": "206CA11117FF",
    "Platform": "ST",
    "Timestamp": 1696691994000
  },
  {
    "Name": "",
    "Discoverer": "Binder198",
    "Glyphs": "2072A11117FF",
    "Platform": "ST",
    "Timestamp": 1712258012000
  },
  {
    "Name": "",
    "Discoverer": "SpicySpaceSnake",
    "Glyphs": "2079A11117FF",
    "Platform": "ST",
    "Timestamp": 1702451514000
  },
  {
    "Name": "",
    "Discoverer": "SpicySpaceSnake",
    "Glyphs": "2079A11117FF",
    "Platform": "ST",
    "Timestamp": 1702451544000
  },
  {
    "Name": "",
    "Discoverer": "SpicySpaceSnake",
    "Glyphs": "2079A11117FF",
    "Platform": "ST",
    "Timestamp": 1702451552000
  },
  {
    "Name": "",
    "Discoverer": "SpicySpaceSnake",
    "Glyphs": "2079A11117FF",
    "Platform": "ST",
    "Timestamp": 1702451578000
  },
  {
    "Name": "",
    "Discoverer": "SpicySpaceSnake",
    "Glyphs": "2079A11117FF",
    "Platform": "ST",
    "Timestamp": 1702451587000
  },
  {
    "Name": "",
    "Discoverer": "SpicySpaceSnake",
    "Glyphs": "2079A11117FF",
    "Platform": "ST",
    "Timestamp": 1702451592000
  },
  {
    "Name": "",
    "Discoverer": "Binder198",
    "Glyphs": "207FA11117FF",
    "Platform": "ST",
    "Timestamp": 1700007224000
  },
  {
    "Name": "",
    "Discoverer": "Binder198",
    "Glyphs": "207FA11117FF",
    "Platform": "ST",
    "Timestamp": 1700007230000
  },
  {
    "Name": "",
    "Discoverer": "Binder198",
    "Glyphs": "207FA11117FF",
    "Platform": "ST",
    "Timestamp": 1700007237000
  },
  {
    "Name": "",
    "Discoverer": "Binder198",
    "Glyphs": "2096A11117FF",
    "Platform": "ST",
    "Timestamp": 1700092499000
  },
  {
    "Name": "",
    "Discoverer": "Binder198",
    "Glyphs": "2096A11117FF",
    "Platform": "ST",
    "Timestamp": 1700092515000
  },
  {
    "Name": "",
    "Discoverer": "Binder198",
    "Glyphs": "2096A11117FF",
    "Platform": "ST",
    "Timestamp": 1700092523000
  },
  {
    "Name": "",
    "Discoverer": "Binder198",
    "Glyphs": "2096A11117FF",
    "Platform": "ST",
    "Timestamp": 1700092539000
  },
  {
    "Name": "",
    "Discoverer": "Binder198",
    "Glyphs": "2096A11117FF",
    "Platform": "ST",
    "Timestamp": 1700092546000
  },
  {
    "Name": "",
    "Discoverer": "Binder198",
    "Glyphs": "20B1A11117FF",
    "Platform": "ST",
    "Timestamp": 1700313561000
  },
  {
    "Name": "",
    "Discoverer": "Lenni",
    "Glyphs": "20B9A11117FF",
    "Platform": "ST",
    "Timestamp": 1697884288000
  },
  {
    "Name": "",
    "Discoverer": "Lenni",
    "Glyphs": "20B9A11117FF",
    "Platform": "ST",
    "Timestamp": 1697884294000
  },
  {
    "Name": "",
    "Discoverer": "Binder198",
    "Glyphs": "20BDA11117FF",
    "Platform": "ST",
    "Timestamp": 1700314239000
  },
  {
    "Name": "",
    "Discoverer": "Binder198",
    "Glyphs": "20BEA11117FF",
    "Platform": "ST",
    "Timestamp": 1700006873000
  },
  {
    "Name": "",
    "Discoverer": "Lunivore",
    "Glyphs": "20CDA11117FF",
    "Platform": "ST",
    "Timestamp": 1697390473000
  },
  {
    "Name": "",
    "Discoverer": "Lunivore",
    "Glyphs": "20CDA11117FF",
    "Platform": "ST",
    "Timestamp": 1697390506000
  },
  {
    "Name": "",
    "Discoverer": "Lunivore",
    "Glyphs": "20CDA11117FF",
    "Platform": "ST",
    "Timestamp": 1697390764000
  },
  {
    "Name": "",
    "Discoverer": "Binder198",
    "Glyphs": "20D7A11117FF",
    "Platform": "ST",
    "Timestamp": 1700090815000
  },
  {
    "Name": "",
    "Discoverer": "Binder198",
    "Glyphs": "20D7A11117FF",
    "Platform": "ST",
    "Timestamp": 1700090824000
  },
  {
    "Name": "",
    "Discoverer": "LordDraCool241",
    "Glyphs": "20DFA11117FF",
    "Platform": "XB",
    "Timestamp": 1712526562000
  },
  {
    "Name": "",
    "Discoverer": "LordDraCool241",
    "Glyphs": "20DFA11117FF",
    "Platform": "XB",
    "Timestamp": 1712526576000
  },
  {
    "Name": "",
    "Discoverer": "Binder198",
    "Glyphs": "20E4A11117FF",
    "Platform": "ST",
    "Timestamp": 1700006593000
  },
  {
    "Name": "",
    "Discoverer": "Binder198",
    "Glyphs": "20E4A11117FF",
    "Platform": "ST",
    "Timestamp": 1700006630000
  },
  {
    "Name": "",
    "Discoverer": "Lunivore",
    "Glyphs": "20ECA11117FF",
    "Platform": "ST",
    "Timestamp": 1696864276000
  },
  {
    "Name": "",
    "Discoverer": "Lunivore",
    "Glyphs": "20ECA11117FF",
    "Platform": "ST",
    "Timestamp": 1696864291000
  },
  {
    "Name": "",
    "Discoverer": "Lunivore",
    "Glyphs": "20ECA11117FF",
    "Platform": "ST",
    "Timestamp": 1696864300000
  },
  {
    "Name": "",
    "Discoverer": "Lunivore",
    "Glyphs": "20ECA11117FF",
    "Platform": "ST",
    "Timestamp": 1696864331000
  },
  {
    "Name": "",
    "Discoverer": "Lunivore",
    "Glyphs": "20ECA11117FF",
    "Platform": "ST",
    "Timestamp": 1696864344000
  },
  {
    "Name": "",
    "Discoverer": "Lunivore",
    "Glyphs": "20ECA11117FF",
    "Platform": "ST",
    "Timestamp": 1696864372000
  },
  {
    "Name": "",
    "Discoverer": "Binder198",
    "Glyphs": "2107A11117FF",
    "Platform": "ST",
    "Timestamp": 1700090737000
  },
  {
    "Name": "",
    "Discoverer": "Lunivore",
    "Glyphs": "212BA11117FF",
    "Platform": "ST",
    "Timestamp": 1696857170000
  },
  {
    "Name": "",
    "Discoverer": "Lunivore",
    "Glyphs": "212BA11117FF",
    "Platform": "ST",
    "Timestamp": 1696857190000
  },
  {
    "Name": "",
    "Discoverer": "Lunivore",
    "Glyphs": "212BA11117FF",
    "Platform": "ST",
    "Timestamp": 1696857200000
  },
  {
    "Name": "",
    "Discoverer": "Binder198",
    "Glyphs": "2149A11117FF",
    "Platform": "ST",
    "Timestamp": 1700007448000
  },
  {
    "Name": "",
    "Discoverer": "Lunivore",
    "Glyphs": "214FA11117FF",
    "Platform": "ST",
    "Timestamp": 1696181985000
  },
  {
    "Name": "",
    "Discoverer": "Lunivore",
    "Glyphs": "214FA11117FF",
    "Platform": "ST",
    "Timestamp": 1696182029000
  },
  {
    "Name": "",
    "Discoverer": "Lunivore",
    "Glyphs": "2151A11117FF",
    "Platform": "ST",
    "Timestamp": 1695752824000
  },
  {
    "Name": "",
    "Discoverer": "Lunivore",
    "Glyphs": "2151A11117FF",
    "Platform": "ST",
    "Timestamp": 1695752843000
  },
  {
    "Name": "",
    "Discoverer": "Lunivore",
    "Glyphs": "2151A11117FF",
    "Platform": "ST",
    "Timestamp": 1695752854000
  },
  {
    "Name": "",
    "Discoverer": "Lunivore",
    "Glyphs": "2151A11117FF",
    "Platform": "ST",
    "Timestamp": 1695752872000
  },
  {
    "Name": "",
    "Discoverer": "Lunivore",
    "Glyphs": "2151A11117FF",
    "Platform": "ST",
    "Timestamp": 1695752887000
  },
  {
    "Name": "",
    "Discoverer": "Lunivore",
    "Glyphs": "2151A11117FF",
    "Platform": "ST",
    "Timestamp": 1695752894000
  },
  {
    "Name": "",
    "Discoverer": "Lunivore",
    "Glyphs": "2151A11117FF",
    "Platform": "ST",
    "Timestamp": 1695752922000
  },
  {
    "Name": "",
    "Discoverer": "Lunivore",
    "Glyphs": "2151A11117FF",
    "Platform": "ST",
    "Timestamp": 1695754002000
  },
  {
    "Name": "",
    "Discoverer": "Lunivore",
    "Glyphs": "2151A11117FF",
    "Platform": "ST",
    "Timestamp": 1695754011000
  },
  {
    "Name": "",
    "Discoverer": "Lunivore",
    "Glyphs": "2151A11117FF",
    "Platform": "ST",
    "Timestamp": 1695754024000
  },
  {
    "Name": "",
    "Discoverer": "Lunivore",
    "Glyphs": "2152A11117FF",
    "Platform": "ST",
    "Timestamp": 1708777519000
  },
  {
    "Name": "",
    "Discoverer": "Lunivore",
    "Glyphs": "2152A11117FF",
    "Platform": "ST",
    "Timestamp": 1708777533000
  },
  {
    "Name": "",
    "Discoverer": "Lunivore",
    "Glyphs": "2152A11117FF",
    "Platform": "ST",
    "Timestamp": 1708777541000
  },
  {
    "Name": "",
    "Discoverer": "Lunivore",
    "Glyphs": "2152A11117FF",
    "Platform": "ST",
    "Timestamp": 1708777548000
  },
  {
    "Name": "",
    "Discoverer": "Lunivore",
    "Glyphs": "2152A11117FF",
    "Platform": "ST",
    "Timestamp": 1708777605000
  },
  {
    "Name": "",
    "Discoverer": "Lunivore",
    "Glyphs": "2152A11117FF",
    "Platform": "ST",
    "Timestamp": 1708777634000
  },
  {
    "Name": "",
    "Discoverer": "Binder198",
    "Glyphs": "217DA11117FF",
    "Platform": "ST",
    "Timestamp": 1712151550000
  },
  {
    "Name": "",
    "Discoverer": "Binder198",
    "Glyphs": "217DA11117FF",
    "Platform": "ST",
    "Timestamp": 1712151555000
  },
  {
    "Name": "",
    "Discoverer": "Binder198",
    "Glyphs": "217DA11117FF",
    "Platform": "ST",
    "Timestamp": 1712151563000
  },
  {
    "Name": "",
    "Discoverer": "Binder198",
    "Glyphs": "217DA11117FF",
    "Platform": "ST",
    "Timestamp": 1712151573000
  },
  {
    "Name": "",
    "Discoverer": "Binder198",
    "Glyphs": "2181A11117FF",
    "Platform": "ST",
    "Timestamp": 1712493924000
  },
  {
    "Name": "",
    "Discoverer": "YucaFrita",
    "Glyphs": "218BA11117FF",
    "Platform": "ST",
    "Timestamp": 1711816442000
  },
  {
    "Name": "",
    "Discoverer": "YucaFrita",
    "Glyphs": "218BA11117FF",
    "Platform": "ST",
    "Timestamp": 1711816449000
  },
  {
    "Name": "",
    "Discoverer": "YucaFrita",
    "Glyphs": "218BA11117FF",
    "Platform": "ST",
    "Timestamp": 1711816454000
  },
  {
    "Name": "",
    "Discoverer": "YucaFrita",
    "Glyphs": "218BA11117FF",
    "Platform": "ST",
    "Timestamp": 1711816463000
  },
  {
    "Name": "",
    "Discoverer": "YucaFrita",
    "Glyphs": "218BA11117FF",
    "Platform": "ST",
    "Timestamp": 1711816469000
  },
  {
    "Name": "",
    "Discoverer": "YucaFrita",
    "Glyphs": "218BA11117FF",
    "Platform": "ST",
    "Timestamp": 1711816479000
  },
  {
    "Name": "",
    "Discoverer": "YucaFrita",
    "Glyphs": "218BA11117FF",
    "Platform": "ST",
    "Timestamp": 1711816485000
  },
  {
    "Name": "",
    "Discoverer": "YucaFrita",
    "Glyphs": "218BA11117FF",
    "Platform": "ST",
    "Timestamp": 1711816495000
  },
  {
    "Name": "",
    "Discoverer": "YucaFrita",
    "Glyphs": "218BA11117FF",
    "Platform": "ST",
    "Timestamp": 1711816502000
  },
  {
    "Name": "",
    "Discoverer": "Binder198",
    "Glyphs": "3021A11117FF",
    "Platform": "ST",
    "Timestamp": 1712258143000
  },
  {
    "Name": "",
    "Discoverer": "Lunivore",
    "Glyphs": "3043A11117FF",
    "Platform": "ST",
    "Timestamp": 1703258726000
  },
  {
    "Name": "",
    "Discoverer": "Lunivore",
    "Glyphs": "3043A11117FF",
    "Platform": "ST",
    "Timestamp": 1703258753000
  },
  {
    "Name": "",
    "Discoverer": "Lunivore",
    "Glyphs": "3043A11117FF",
    "Platform": "ST",
    "Timestamp": 1703258782000
  },
  {
    "Name": "",
    "Discoverer": "Lunivore",
    "Glyphs": "3052A11117FF",
    "Platform": "ST",
    "Timestamp": 1698866058000
  },
  {
    "Name": "",
    "Discoverer": "Lunivore",
    "Glyphs": "3052A11117FF",
    "Platform": "ST",
    "Timestamp": 1698866066000
  },
  {
    "Name": "",
    "Discoverer": "Lunivore",
    "Glyphs": "3052A11117FF",
    "Platform": "ST",
    "Timestamp": 1698866131000
  },
  {
    "Name": "",
    "Discoverer": "Lunivore",
    "Glyphs": "3052A11117FF",
    "Platform": "ST",
    "Timestamp": 1698866144000
  },
  {
    "Name": "",
    "Discoverer": "YucaFrita",
    "Glyphs": "3054A11117FF",
    "Platform": "ST",
    "Timestamp": 1700311768000
  },
  {
    "Name": "",
    "Discoverer": "YucaFrita",
    "Glyphs": "3054A11117FF",
    "Platform": "ST",
    "Timestamp": 1700311773000
  },
  {
    "Name": "",
    "Discoverer": "YucaFrita",
    "Glyphs": "3054A11117FF",
    "Platform": "ST",
    "Timestamp": 1700311780000
  },
  {
    "Name": "",
    "Discoverer": "YucaFrita",
    "Glyphs": "3054A11117FF",
    "Platform": "ST",
    "Timestamp": 1700311789000
  },
  {
    "Name": "",
    "Discoverer": "YucaFrita",
    "Glyphs": "3054A11117FF",
    "Platform": "ST",
    "Timestamp": 1700311796000
  },
  {
    "Name": "",
    "Discoverer": "YucaFrita",
    "Glyphs": "3054A11117FF",
    "Platform": "ST",
    "Timestamp": 1700311802000
  },
  {
    "Name": "",
    "Discoverer": "YucaFrita",
    "Glyphs": "3054A11117FF",
    "Platform": "ST",
    "Timestamp": 1700311811000
  },
  {
    "Name": "",
    "Discoverer": "YucaFrita",
    "Glyphs": "3054A11117FF",
    "Platform": "ST",
    "Timestamp": 1700311817000
  },
  {
    "Name": "",
    "Discoverer": "YucaFrita",
    "Glyphs": "3054A11117FF",
    "Platform": "ST",
    "Timestamp": 1700311825000
  },
  {
    "Name": "",
    "Discoverer": "YucaFrita",
    "Glyphs": "3054A11117FF",
    "Platform": "ST",
    "Timestamp": 1700311831000
  },
  {
    "Name": "",
    "Discoverer": "YucaFrita",
    "Glyphs": "3054A11117FF",
    "Platform": "ST",
    "Timestamp": 1700311836000
  },
  {
    "Name": "",
    "Discoverer": "YucaFrita",
    "Glyphs": "3054A11117FF",
    "Platform": "ST",
    "Timestamp": 1700311844000
  },
  {
    "Name": "",
    "Discoverer": "Binder198",
    "Glyphs": "3057A11117FF",
    "Platform": "ST",
    "Timestamp": 1709562019000
  },
  {
    "Name": "",
    "Discoverer": "Lunivore",
    "Glyphs": "3062A11117FF",
    "Platform": "ST",
    "Timestamp": 1696852236000
  },
  {
    "Name": "",
    "Discoverer": "Lunivore",
    "Glyphs": "3062A11117FF",
    "Platform": "ST",
    "Timestamp": 1696852251000
  },
  {
    "Name": "",
    "Discoverer": "Lunivore",
    "Glyphs": "3062A11117FF",
    "Platform": "ST",
    "Timestamp": 1696852306000
  },
  {
    "Name": "",
    "Discoverer": "Lunivore",
    "Glyphs": "3062A11117FF",
    "Platform": "ST",
    "Timestamp": 1696852332000
  },
  {
    "Name": "",
    "Discoverer": "Lunivore",
    "Glyphs": "3062A11117FF",
    "Platform": "ST",
    "Timestamp": 1696852361000
  },
  {
    "Name": "",
    "Discoverer": "Lunivore",
    "Glyphs": "306CA11117FF",
    "Platform": "ST",
    "Timestamp": 1696752876000
  },
  {
    "Name": "",
    "Discoverer": "Lunivore",
    "Glyphs": "306CA11117FF",
    "Platform": "ST",
    "Timestamp": 1696752885000
  },
  {
    "Name": "",
    "Discoverer": "Binder198",
    "Glyphs": "30C4A11117FF",
    "Platform": "ST",
    "Timestamp": 1700314033000
  },
  {
    "Name": "",
    "Discoverer": "Lunivore",
    "Glyphs": "30CDA11117FF",
    "Platform": "ST",
    "Timestamp": 1697390794000
  },
  {
    "Name": "",
    "Discoverer": "Lunivore",
    "Glyphs": "30CDA11117FF",
    "Platform": "ST",
    "Timestamp": 1697390803000
  },
  {
    "Name": "",
    "Discoverer": "Lunivore",
    "Glyphs": "30ECA11117FF",
    "Platform": "ST",
    "Timestamp": 1696860842000
  },
  {
    "Name": "",
    "Discoverer": "Lunivore",
    "Glyphs": "30ECA11117FF",
    "Platform": "ST",
    "Timestamp": 1696860852000
  },
  {
    "Name": "",
    "Discoverer": "Lunivore",
    "Glyphs": "30ECA11117FF",
    "Platform": "ST",
    "Timestamp": 1696860865000
  },
  {
    "Name": "",
    "Discoverer": "Lunivore",
    "Glyphs": "30ECA11117FF",
    "Platform": "ST",
    "Timestamp": 1696860875000
  },
  {
    "Name": "",
    "Discoverer": "Binder198",
    "Glyphs": "3109A11117FF",
    "Platform": "ST",
    "Timestamp": 1700090322000
  },
  {
    "Name": "",
    "Discoverer": "Binder198",
    "Glyphs": "3109A11117FF",
    "Platform": "ST",
    "Timestamp": 1700090330000
  },
  {
    "Name": "",
    "Discoverer": "Binder198",
    "Glyphs": "3109A11117FF",
    "Platform": "ST",
    "Timestamp": 1700090345000
  },
  {
    "Name": "",
    "Discoverer": "Binder198",
    "Glyphs": "3109A11117FF",
    "Platform": "ST",
    "Timestamp": 1700090363000
  },
  {
    "Name": "",
    "Discoverer": "Lunivore",
    "Glyphs": "314FA11117FF",
    "Platform": "ST",
    "Timestamp": 1696181482000
  },
  {
    "Name": "",
    "Discoverer": "Lunivore",
    "Glyphs": "314FA11117FF",
    "Platform": "ST",
    "Timestamp": 1696181502000
  },
  {
    "Name": "",
    "Discoverer": "Lunivore",
    "Glyphs": "314FA11117FF",
    "Platform": "ST",
    "Timestamp": 1696181536000
  },
  {
    "Name": "",
    "Discoverer": "Lunivore",
    "Glyphs": "314FA11117FF",
    "Platform": "ST",
    "Timestamp": 1696181563000
  },
  {
    "Name": "",
    "Discoverer": "Lunivore",
    "Glyphs": "314FA11117FF",
    "Platform": "ST",
    "Timestamp": 1696181570000
  },
  {
    "Name": "",
    "Discoverer": "Lunivore",
    "Glyphs": "3152A11117FF",
    "Platform": "ST",
    "Timestamp": 1708801724000
  },
  {
    "Name": "",
    "Discoverer": "Lunivore",
    "Glyphs": "3152A11117FF",
    "Platform": "ST",
    "Timestamp": 1708801732000
  },
  {
    "Name": "",
    "Discoverer": "Lunivore",
    "Glyphs": "3152A11117FF",
    "Platform": "ST",
    "Timestamp": 1708801747000
  },
  {
    "Name": "",
    "Discoverer": "Lunivore",
    "Glyphs": "3152A11117FF",
    "Platform": "ST",
    "Timestamp": 1708801755000
  },
  {
    "Name": "",
    "Discoverer": "Lunivore",
    "Glyphs": "3152A11117FF",
    "Platform": "ST",
    "Timestamp": 1708801772000
  },
  {
    "Name": "",
    "Discoverer": "Lunivore",
    "Glyphs": "3152A11117FF",
    "Platform": "ST",
    "Timestamp": 1708801894000
  },
  {
    "Name": "",
    "Discoverer": "Lunivore",
    "Glyphs": "3152A11117FF",
    "Platform": "ST",
    "Timestamp": 1708801900000
  },
  {
    "Name": "",
    "Discoverer": "Lunivore",
    "Glyphs": "3152A11117FF",
    "Platform": "ST",
    "Timestamp": 1708801906000
  },
  {
    "Name": "",
    "Discoverer": "Lunivore",
    "Glyphs": "3152A11117FF",
    "Platform": "ST",
    "Timestamp": 1708801915000
  },
  {
    "Name": "",
    "Discoverer": "LordDraCool241",
    "Glyphs": "3160A11117FF",
    "Platform": "XB",
    "Timestamp": 1713870424000
  },
  {
    "Name": "",
    "Discoverer": "Binder198",
    "Glyphs": "317AA11117FF",
    "Platform": "ST",
    "Timestamp": 1711798060000
  },
  {
    "Name": "",
    "Discoverer": "Binder198",
    "Glyphs": "317AA11117FF",
    "Platform": "ST",
    "Timestamp": 1711798070000
  },
  {
    "Name": "",
    "Discoverer": "Binder198",
    "Glyphs": "317AA11117FF",
    "Platform": "ST",
    "Timestamp": 1711798077000
  },
  {
    "Name": "",
    "Discoverer": "Binder198",
    "Glyphs": "317AA11117FF",
    "Platform": "ST",
    "Timestamp": 1711798084000
  },
  {
    "Name": "",
    "Discoverer": "YucaFrita",
    "Glyphs": "4001A11117FF",
    "Platform": "ST",
    "Timestamp": 1695936236000
  },
  {
    "Name": "",
    "Discoverer": "YucaFrita",
    "Glyphs": "4001A11117FF",
    "Platform": "ST",
    "Timestamp": 1695936244000
  },
  {
    "Name": "",
    "Discoverer": "YucaFrita",
    "Glyphs": "4001A11117FF",
    "Platform": "ST",
    "Timestamp": 1695936253000
  },
  {
    "Name": "",
    "Discoverer": "YucaFrita",
    "Glyphs": "4001A11117FF",
    "Platform": "ST",
    "Timestamp": 1695936261000
  },
  {
    "Name": "",
    "Discoverer": "YucaFrita",
    "Glyphs": "4001A11117FF",
    "Platform": "ST",
    "Timestamp": 1695936268000
  },
  {
    "Name": "",
    "Discoverer": "YucaFrita",
    "Glyphs": "4001A11117FF",
    "Platform": "ST",
    "Timestamp": 1695936274000
  },
  {
    "Name": "",
    "Discoverer": "Binder198",
    "Glyphs": "4008A11117FF",
    "Platform": "ST",
    "Timestamp": 1700091781000
  },
  {
    "Name": "",
    "Discoverer": "Lunivore",
    "Glyphs": "400BA11117FF",
    "Platform": "ST",
    "Timestamp": 1697359778000
  },
  {
    "Name": "",
    "Discoverer": "Lunivore",
    "Glyphs": "400BA11117FF",
    "Platform": "ST",
    "Timestamp": 1697359794000
  },
  {
    "Name": "",
    "Discoverer": "Lunivore",
    "Glyphs": "400BA11117FF",
    "Platform": "ST",
    "Timestamp": 1697359809000
  },
  {
    "Name": "",
    "Discoverer": "Lunivore",
    "Glyphs": "400BA11117FF",
    "Platform": "ST",
    "Timestamp": 1697359831000
  },
  {
    "Name": "",
    "Discoverer": "Binder198",
    "Glyphs": "4010A11117FF",
    "Platform": "ST",
    "Timestamp": 1711996907000
  },
  {
    "Name": "",
    "Discoverer": "Binder198",
    "Glyphs": "4010A11117FF",
    "Platform": "ST",
    "Timestamp": 1711996913000
  },
  {
    "Name": "",
    "Discoverer": "Binder198",
    "Glyphs": "4010A11117FF",
    "Platform": "ST",
    "Timestamp": 1711996920000
  },
  {
    "Name": "",
    "Discoverer": "Binder198",
    "Glyphs": "4010A11117FF",
    "Platform": "ST",
    "Timestamp": 1711996926000
  },
  {
    "Name": "",
    "Discoverer": "Binder198",
    "Glyphs": "4010A11117FF",
    "Platform": "ST",
    "Timestamp": 1711996961000
  },
  {
    "Name": "",
    "Discoverer": "Binder198",
    "Glyphs": "4021A11117FF",
    "Platform": "ST",
    "Timestamp": 1712258744000
  },
  {
    "Name": "",
    "Discoverer": "Binder198",
    "Glyphs": "4021A11117FF",
    "Platform": "ST",
    "Timestamp": 1712258770000
  },
  {
    "Name": "",
    "Discoverer": "Binder198",
    "Glyphs": "4021A11117FF",
    "Platform": "ST",
    "Timestamp": 1712258775000
  },
  {
    "Name": "",
    "Discoverer": "Lunivore",
    "Glyphs": "4043A11117FF",
    "Platform": "ST",
    "Timestamp": 1703259913000
  },
  {
    "Name": "",
    "Discoverer": "Lunivore",
    "Glyphs": "4043A11117FF",
    "Platform": "ST",
    "Timestamp": 1703259921000
  },
  {
    "Name": "",
    "Discoverer": "Lunivore",
    "Glyphs": "4043A11117FF",
    "Platform": "ST",
    "Timestamp": 1703259943000
  },
  {
    "Name": "",
    "Discoverer": "Lunivore",
    "Glyphs": "4043A11117FF",
    "Platform": "ST",
    "Timestamp": 1703259949000
  },
  {
    "Name": "",
    "Discoverer": "Lunivore",
    "Glyphs": "4043A11117FF",
    "Platform": "ST",
    "Timestamp": 1703259964000
  },
  {
    "Name": "",
    "Discoverer": "Lunivore",
    "Glyphs": "4043A11117FF",
    "Platform": "ST",
    "Timestamp": 1703259983000
  },
  {
    "Name": "",
    "Discoverer": "Lunivore",
    "Glyphs": "4043A11117FF",
    "Platform": "ST",
    "Timestamp": 1703260011000
  },
  {
    "Name": "",
    "Discoverer": "Lunivore",
    "Glyphs": "4043A11117FF",
    "Platform": "ST",
    "Timestamp": 1703260026000
  },
  {
    "Name": "",
    "Discoverer": "Lunivore",
    "Glyphs": "4052A11117FF",
    "Platform": "ST",
    "Timestamp": 1698866170000
  },
  {
    "Name": "",
    "Discoverer": "Lunivore",
    "Glyphs": "4052A11117FF",
    "Platform": "ST",
    "Timestamp": 1698866222000
  },
  {
    "Name": "",
    "Discoverer": "Lunivore",
    "Glyphs": "4052A11117FF",
    "Platform": "ST",
    "Timestamp": 1698866245000
  },
  {
    "Name": "",
    "Discoverer": "Lunivore",
    "Glyphs": "4052A11117FF",
    "Platform": "ST",
    "Timestamp": 1698866252000
  },
  {
    "Name": "",
    "Discoverer": "Lunivore",
    "Glyphs": "4052A11117FF",
    "Platform": "ST",
    "Timestamp": 1698866266000
  },
  {
    "Name": "",
    "Discoverer": "Lunivore",
    "Glyphs": "4052A11117FF",
    "Platform": "ST",
    "Timestamp": 1698866290000
  },
  {
    "Name": "",
    "Discoverer": "Lunivore",
    "Glyphs": "4052A11117FF",
    "Platform": "ST",
    "Timestamp": 1698866305000
  },
  {
    "Name": "",
    "Discoverer": "Lunivore",
    "Glyphs": "4052A11117FF",
    "Platform": "ST",
    "Timestamp": 1698866328000
  },
  {
    "Name": "",
    "Discoverer": "Lunivore",
    "Glyphs": "4052A11117FF",
    "Platform": "ST",
    "Timestamp": 1698866608000
  },
  {
    "Name": "",
    "Discoverer": "Lunivore",
    "Glyphs": "4052A11117FF",
    "Platform": "ST",
    "Timestamp": 1698866625000
  },
  {
    "Name": "",
    "Discoverer": "Lunivore",
    "Glyphs": "4052A11117FF",
    "Platform": "ST",
    "Timestamp": 1698866641000
  },
  {
    "Name": "",
    "Discoverer": "Lunivore",
    "Glyphs": "4052A11117FF",
    "Platform": "ST",
    "Timestamp": 1698866657000
  },
  {
    "Name": "",
    "Discoverer": "Lunivore",
    "Glyphs": "4052A11117FF",
    "Platform": "ST",
    "Timestamp": 1698866669000
  },
  {
    "Name": "",
    "Discoverer": "Binder198",
    "Glyphs": "4059A11117FF",
    "Platform": "ST",
    "Timestamp": 1711797782000
  },
  {
    "Name": "",
    "Discoverer": "Binder198",
    "Glyphs": "4059A11117FF",
    "Platform": "ST",
    "Timestamp": 1711797788000
  },
  {
    "Name": "",
    "Discoverer": "Binder198",
    "Glyphs": "4059A11117FF",
    "Platform": "ST",
    "Timestamp": 1711797802000
  },
  {
    "Name": "",
    "Discoverer": "Binder198",
    "Glyphs": "4059A11117FF",
    "Platform": "ST",
    "Timestamp": 1711797810000
  },
  {
    "Name": "",
    "Discoverer": "Lunivore",
    "Glyphs": "4062A11117FF",
    "Platform": "ST",
    "Timestamp": 1696854787000
  },
  {
    "Name": "",
    "Discoverer": "Lunivore",
    "Glyphs": "4062A11117FF",
    "Platform": "ST",
    "Timestamp": 1696854797000
  },
  {
    "Name": "",
    "Discoverer": "Lunivore",
    "Glyphs": "4062A11117FF",
    "Platform": "ST",
    "Timestamp": 1696854820000
  },
  {
    "Name": "",
    "Discoverer": "Lunivore",
    "Glyphs": "4062A11117FF",
    "Platform": "ST",
    "Timestamp": 1696854874000
  },
  {
    "Name": "",
    "Discoverer": "Lunivore",
    "Glyphs": "4062A11117FF",
    "Platform": "ST",
    "Timestamp": 1696854892000
  },
  {
    "Name": "",
    "Discoverer": "Lunivore",
    "Glyphs": "4062A11117FF",
    "Platform": "ST",
    "Timestamp": 1696854907000
  },
  {
    "Name": "",
    "Discoverer": "Lunivore",
    "Glyphs": "4062A11117FF",
    "Platform": "ST",
    "Timestamp": 1696854912000
  },
  {
    "Name": "",
    "Discoverer": "Lunivore",
    "Glyphs": "4062A11117FF",
    "Platform": "ST",
    "Timestamp": 1696854928000
  },
  {
    "Name": "",
    "Discoverer": "Lunivore",
    "Glyphs": "4062A11117FF",
    "Platform": "ST",
    "Timestamp": 1696854950000
  },
  {
    "Name": "",
    "Discoverer": "Lunivore",
    "Glyphs": "406CA11117FF",
    "Platform": "ST",
    "Timestamp": 1696327489000
  },
  {
    "Name": "",
    "Discoverer": "Lunivore",
    "Glyphs": "406CA11117FF",
    "Platform": "ST",
    "Timestamp": 1696327500000
  },
  {
    "Name": "",
    "Discoverer": "Lunivore",
    "Glyphs": "406CA11117FF",
    "Platform": "ST",
    "Timestamp": 1696327510000
  },
  {
    "Name": "",
    "Discoverer": "Lunivore",
    "Glyphs": "406CA11117FF",
    "Platform": "ST",
    "Timestamp": 1696327514000
  },
  {
    "Name": "",
    "Discoverer": "Lunivore",
    "Glyphs": "406CA11117FF",
    "Platform": "ST",
    "Timestamp": 1696327522000
  },
  {
    "Name": "",
    "Discoverer": "Lunivore",
    "Glyphs": "406CA11117FF",
    "Platform": "ST",
    "Timestamp": 1696327527000
  },
  {
    "Name": "",
    "Discoverer": "Lunivore",
    "Glyphs": "406CA11117FF",
    "Platform": "ST",
    "Timestamp": 1696327534000
  },
  {
    "Name": "",
    "Discoverer": "Lunivore",
    "Glyphs": "406CA11117FF",
    "Platform": "ST",
    "Timestamp": 1696327541000
  },
  {
    "Name": "",
    "Discoverer": "Lunivore",
    "Glyphs": "406CA11117FF",
    "Platform": "ST",
    "Timestamp": 1696327548000
  },
  {
    "Name": "",
    "Discoverer": "Lunivore",
    "Glyphs": "406CA11117FF",
    "Platform": "ST",
    "Timestamp": 1696327556000
  },
  {
    "Name": "",
    "Discoverer": "Binder198",
    "Glyphs": "40BEA11117FF",
    "Platform": "ST",
    "Timestamp": 1700006886000
  },
  {
    "Name": "",
    "Discoverer": "Lunivore",
    "Glyphs": "40CDA11117FF",
    "Platform": "ST",
    "Timestamp": 1697292835000
  },
  {
    "Name": "",
    "Discoverer": "Lunivore",
    "Glyphs": "40CDA11117FF",
    "Platform": "ST",
    "Timestamp": 1697292895000
  },
  {
    "Name": "",
    "Discoverer": "Lunivore",
    "Glyphs": "40CDA11117FF",
    "Platform": "ST",
    "Timestamp": 1697295445000
  },
  {
    "Name": "",
    "Discoverer": "Lunivore",
    "Glyphs": "40CDA11117FF",
    "Platform": "ST",
    "Timestamp": 1697295468000
  },
  {
    "Name": "",
    "Discoverer": "Lunivore",
    "Glyphs": "40CDA11117FF",
    "Platform": "ST",
    "Timestamp": 1697295490000
  },
  {
    "Name": "",
    "Discoverer": "Lunivore",
    "Glyphs": "40CDA11117FF",
    "Platform": "ST",
    "Timestamp": 1697295516000
  },
  {
    "Name": "",
    "Discoverer": "Lunivore",
    "Glyphs": "40CDA11117FF",
    "Platform": "ST",
    "Timestamp": 1697295523000
  },
  {
    "Name": "",
    "Discoverer": "Lunivore",
    "Glyphs": "40CDA11117FF",
    "Platform": "ST",
    "Timestamp": 1697295528000
  },
  {
    "Name": "",
    "Discoverer": "Lunivore",
    "Glyphs": "40CDA11117FF",
    "Platform": "ST",
    "Timestamp": 1697295534000
  },
  {
    "Name": "",
    "Discoverer": "Binder198",
    "Glyphs": "40D7A11117FF",
    "Platform": "ST",
    "Timestamp": 1700090904000
  },
  {
    "Name": "",
    "Discoverer": "Lianeras",
    "Glyphs": "40DDA11117FF",
    "Platform": "ST",
    "Timestamp": 1702720243000
  },
  {
    "Name": "",
    "Discoverer": "Lianeras",
    "Glyphs": "40DDA11117FF",
    "Platform": "ST",
    "Timestamp": 1702720262000
  },
  {
    "Name": "",
    "Discoverer": "Lianeras",
    "Glyphs": "40DDA11117FF",
    "Platform": "ST",
    "Timestamp": 1702720269000
  },
  {
    "Name": "",
    "Discoverer": "Lianeras",
    "Glyphs": "40DDA11117FF",
    "Platform": "ST",
    "Timestamp": 1702720279000
  },
  {
    "Name": "",
    "Discoverer": "Lunivore",
    "Glyphs": "40ECA11117FF",
    "Platform": "ST",
    "Timestamp": 1696864186000
  },
  {
    "Name": "",
    "Discoverer": "Lunivore",
    "Glyphs": "40ECA11117FF",
    "Platform": "ST",
    "Timestamp": 1696864191000
  },
  {
    "Name": "",
    "Discoverer": "Lunivore",
    "Glyphs": "40ECA11117FF",
    "Platform": "ST",
    "Timestamp": 1696864222000
  },
  {
    "Name": "",
    "Discoverer": "Lunivore",
    "Glyphs": "40ECA11117FF",
    "Platform": "ST",
    "Timestamp": 1696868590000
  },
  {
    "Name": "",
    "Discoverer": "Lunivore",
    "Glyphs": "40ECA11117FF",
    "Platform": "ST",
    "Timestamp": 1696868595000
  },
  {
    "Name": "",
    "Discoverer": "Binder198",
    "Glyphs": "4102A11117FF",
    "Platform": "ST",
    "Timestamp": 1700006157000
  },
  {
    "Name": "",
    "Discoverer": "Binder198",
    "Glyphs": "4102A11117FF",
    "Platform": "ST",
    "Timestamp": 1700006163000
  },
  {
    "Name": "",
    "Discoverer": "Binder198",
    "Glyphs": "4122A11117FF",
    "Platform": "ST",
    "Timestamp": 1700006992000
  },
  {
    "Name": "",
    "Discoverer": "Binder198",
    "Glyphs": "4124A11117FF",
    "Platform": "ST",
    "Timestamp": 1700090425000
  },
  {
    "Name": "",
    "Discoverer": "Binder198",
    "Glyphs": "4124A11117FF",
    "Platform": "ST",
    "Timestamp": 1700090434000
  },
  {
    "Name": "",
    "Discoverer": "Binder198",
    "Glyphs": "4124A11117FF",
    "Platform": "ST",
    "Timestamp": 1700090442000
  },
  {
    "Name": "",
    "Discoverer": "Binder198",
    "Glyphs": "4124A11117FF",
    "Platform": "ST",
    "Timestamp": 1700090449000
  },
  {
    "Name": "",
    "Discoverer": "Lunivore",
    "Glyphs": "412BA11117FF",
    "Platform": "ST",
    "Timestamp": 1696857729000
  },
  {
    "Name": "",
    "Discoverer": "Lunivore",
    "Glyphs": "412BA11117FF",
    "Platform": "ST",
    "Timestamp": 1696857735000
  },
  {
    "Name": "",
    "Discoverer": "Lunivore",
    "Glyphs": "412BA11117FF",
    "Platform": "ST",
    "Timestamp": 1696857741000
  },
  {
    "Name": "",
    "Discoverer": "Lunivore",
    "Glyphs": "412BA11117FF",
    "Platform": "ST",
    "Timestamp": 1696857747000
  },
  {
    "Name": "",
    "Discoverer": "Lunivore",
    "Glyphs": "412BA11117FF",
    "Platform": "ST",
    "Timestamp": 1696857773000
  },
  {
    "Name": "",
    "Discoverer": "Lunivore",
    "Glyphs": "412BA11117FF",
    "Platform": "ST",
    "Timestamp": 1696857801000
  },
  {
    "Name": "",
    "Discoverer": "Lunivore",
    "Glyphs": "412BA11117FF",
    "Platform": "ST",
    "Timestamp": 1696858332000
  },
  {
    "Name": "",
    "Discoverer": "Lunivore",
    "Glyphs": "412BA11117FF",
    "Platform": "ST",
    "Timestamp": 1696858410000
  },
  {
    "Name": "",
    "Discoverer": "Lunivore",
    "Glyphs": "414FA11117FF",
    "Platform": "ST",
    "Timestamp": 1696181582000
  },
  {
    "Name": "",
    "Discoverer": "Lunivore",
    "Glyphs": "414FA11117FF",
    "Platform": "ST",
    "Timestamp": 1696181590000
  },
  {
    "Name": "",
    "Discoverer": "Lunivore",
    "Glyphs": "414FA11117FF",
    "Platform": "ST",
    "Timestamp": 1696181616000
  },
  {
    "Name": "",
    "Discoverer": "Lunivore",
    "Glyphs": "414FA11117FF",
    "Platform": "ST",
    "Timestamp": 1696181620000
  },
  {
    "Name": "",
    "Discoverer": "Lunivore",
    "Glyphs": "414FA11117FF",
    "Platform": "ST",
    "Timestamp": 1696181628000
  },
  {
    "Name": "",
    "Discoverer": "Lunivore",
    "Glyphs": "414FA11117FF",
    "Platform": "ST",
    "Timestamp": 1696181641000
  },
  {
    "Name": "",
    "Discoverer": "Lunivore",
    "Glyphs": "414FA11117FF",
    "Platform": "ST",
    "Timestamp": 1696181664000
  },
  {
    "Name": "",
    "Discoverer": "Lunivore",
    "Glyphs": "414FA11117FF",
    "Platform": "ST",
    "Timestamp": 1696181679000
  },
  {
    "Name": "",
    "Discoverer": "Lunivore",
    "Glyphs": "414FA11117FF",
    "Platform": "ST",
    "Timestamp": 1696181695000
  },
  {
    "Name": "",
    "Discoverer": "Lunivore",
    "Glyphs": "414FA11117FF",
    "Platform": "ST",
    "Timestamp": 1696181702000
  },
  {
    "Name": "",
    "Discoverer": "YucaFrita",
    "Glyphs": "4182A11117FF",
    "Platform": "ST",
    "Timestamp": 1712394121000
  },
  {
    "Name": "",
    "Discoverer": "YucaFrita",
    "Glyphs": "4182A11117FF",
    "Platform": "ST",
    "Timestamp": 1712394127000
  },
  {
    "Name": "",
    "Discoverer": "YucaFrita",
    "Glyphs": "4182A11117FF",
    "Platform": "ST",
    "Timestamp": 1712394133000
  },
  {
    "Name": "",
    "Discoverer": "YucaFrita",
    "Glyphs": "4182A11117FF",
    "Platform": "ST",
    "Timestamp": 1712394140000
  },
  {
    "Name": "",
    "Discoverer": "YucaFrita",
    "Glyphs": "4182A11117FF",
    "Platform": "ST",
    "Timestamp": 1712394148000
  },
  {
    "Name": "",
    "Discoverer": "YucaFrita",
    "Glyphs": "4182A11117FF",
    "Platform": "ST",
    "Timestamp": 1712394156000
  },
  {
    "Name": "",
    "Discoverer": "YucaFrita",
    "Glyphs": "4182A11117FF",
    "Platform": "ST",
    "Timestamp": 1712394163000
  },
  {
    "Name": "",
    "Discoverer": "YucaFrita",
    "Glyphs": "4182A11117FF",
    "Platform": "ST",
    "Timestamp": 1712394169000
  },
  {
    "Name": "",
    "Discoverer": "YucaFrita",
    "Glyphs": "4182A11117FF",
    "Platform": "ST",
    "Timestamp": 1712394175000
  },
  {
    "Name": "",
    "Discoverer": "YucaFrita",
    "Glyphs": "4182A11117FF",
    "Platform": "ST",
    "Timestamp": 1712394182000
  },
  {
    "Name": "",
    "Discoverer": "YucaFrita",
    "Glyphs": "4182A11117FF",
    "Platform": "ST",
    "Timestamp": 1712394192000
  },
  {
    "Name": "",
    "Discoverer": "YucaFrita",
    "Glyphs": "418BA11117FF",
    "Platform": "ST",
    "Timestamp": 1711813323000
  },
  {
    "Name": "",
    "Discoverer": "YucaFrita",
    "Glyphs": "418BA11117FF",
    "Platform": "ST",
    "Timestamp": 1711813330000
  },
  {
    "Name": "",
    "Discoverer": "YucaFrita",
    "Glyphs": "418BA11117FF",
    "Platform": "ST",
    "Timestamp": 1711813338000
  },
  {
    "Name": "",
    "Discoverer": "YucaFrita",
    "Glyphs": "418BA11117FF",
    "Platform": "ST",
    "Timestamp": 1711813348000
  },
  {
    "Name": "",
    "Discoverer": "YucaFrita",
    "Glyphs": "418BA11117FF",
    "Platform": "ST",
    "Timestamp": 1711813356000
  },
  {
    "Name": "",
    "Discoverer": "YucaFrita",
    "Glyphs": "418BA11117FF",
    "Platform": "ST",
    "Timestamp": 1711813364000
  },
  {
    "Name": "",
    "Discoverer": "YucaFrita",
    "Glyphs": "418BA11117FF",
    "Platform": "ST",
    "Timestamp": 1711813374000
  },
  {
    "Name": "",
    "Discoverer": "YucaFrita",
    "Glyphs": "418BA11117FF",
    "Platform": "ST",
    "Timestamp": 1711813383000
  },
  {
    "Name": "",
    "Discoverer": "YucaFrita",
    "Glyphs": "418BA11117FF",
    "Platform": "ST",
    "Timestamp": 1711813392000
  },
  {
    "Name": "",
    "Discoverer": "YucaFrita",
    "Glyphs": "418BA11117FF",
    "Platform": "ST",
    "Timestamp": 1711813402000
  },
  {
    "Name": "",
    "Discoverer": "YucaFrita",
    "Glyphs": "418BA11117FF",
    "Platform": "ST",
    "Timestamp": 1711813409000
  },
  {
    "Name": "",
    "Discoverer": "YucaFrita",
    "Glyphs": "418BA11117FF",
    "Platform": "ST",
    "Timestamp": 1711813414000
  },
  {
    "Name": "",
    "Discoverer": "YucaFrita",
    "Glyphs": "418BA11117FF",
    "Platform": "ST",
    "Timestamp": 1711813419000
  },
  {
    "Name": "",
    "Discoverer": "YucaFrita",
    "Glyphs": "5001A11117FF",
    "Platform": "ST",
    "Timestamp": 1695936170000
  },
  {
    "Name": "",
    "Discoverer": "YucaFrita",
    "Glyphs": "5001A11117FF",
    "Platform": "ST",
    "Timestamp": 1695936179000
  },
  {
    "Name": "",
    "Discoverer": "YucaFrita",
    "Glyphs": "5001A11117FF",
    "Platform": "ST",
    "Timestamp": 1695936185000
  },
  {
    "Name": "",
    "Discoverer": "YucaFrita",
    "Glyphs": "5001A11117FF",
    "Platform": "ST",
    "Timestamp": 1695936195000
  },
  {
    "Name": "",
    "Discoverer": "YucaFrita",
    "Glyphs": "5001A11117FF",
    "Platform": "ST",
    "Timestamp": 1695936206000
  },
  {
    "Name": "",
    "Discoverer": "YucaFrita",
    "Glyphs": "5001A11117FF",
    "Platform": "ST",
    "Timestamp": 1695936211000
  },
  {
    "Name": "",
    "Discoverer": "YucaFrita",
    "Glyphs": "5001A11117FF",
    "Platform": "ST",
    "Timestamp": 1695936217000
  },
  {
    "Name": "",
    "Discoverer": "YucaFrita",
    "Glyphs": "5001A11117FF",
    "Platform": "ST",
    "Timestamp": 1695936229000
  },
  {
    "Name": "",
    "Discoverer": "Binder198",
    "Glyphs": "5023A11117FF",
    "Platform": "ST",
    "Timestamp": 1712402506000
  },
  {
    "Name": "",
    "Discoverer": "Lunivore",
    "Glyphs": "5043A11117FF",
    "Platform": "ST",
    "Timestamp": 1703259875000
  },
  {
    "Name": "",
    "Discoverer": "Lunivore",
    "Glyphs": "5043A11117FF",
    "Platform": "ST",
    "Timestamp": 1703259889000
  },
  {
    "Name": "",
    "Discoverer": "Lunivore",
    "Glyphs": "5062A11117FF",
    "Platform": "ST",
    "Timestamp": 1696856132000
  },
  {
    "Name": "",
    "Discoverer": "Lunivore",
    "Glyphs": "5062A11117FF",
    "Platform": "ST",
    "Timestamp": 1696856139000
  },
  {
    "Name": "",
    "Discoverer": "Lunivore",
    "Glyphs": "5062A11117FF",
    "Platform": "ST",
    "Timestamp": 1696856178000
  },
  {
    "Name": "",
    "Discoverer": "Lunivore",
    "Glyphs": "5062A11117FF",
    "Platform": "ST",
    "Timestamp": 1696856210000
  },
  {
    "Name": "",
    "Discoverer": "Lunivore",
    "Glyphs": "506CA11117FF",
    "Platform": "ST",
    "Timestamp": 1696326340000
  },
  {
    "Name": "",
    "Discoverer": "Lunivore",
    "Glyphs": "506CA11117FF",
    "Platform": "ST",
    "Timestamp": 1696326349000
  },
  {
    "Name": "",
    "Discoverer": "Lunivore",
    "Glyphs": "506CA11117FF",
    "Platform": "ST",
    "Timestamp": 1696326356000
  },
  {
    "Name": "",
    "Discoverer": "Lunivore",
    "Glyphs": "506CA11117FF",
    "Platform": "ST",
    "Timestamp": 1696326363000
  },
  {
    "Name": "",
    "Discoverer": "Lunivore",
    "Glyphs": "506CA11117FF",
    "Platform": "ST",
    "Timestamp": 1696326371000
  },
  {
    "Name": "",
    "Discoverer": "Lunivore",
    "Glyphs": "506CA11117FF",
    "Platform": "ST",
    "Timestamp": 1696326380000
  },
  {
    "Name": "",
    "Discoverer": "Lunivore",
    "Glyphs": "506CA11117FF",
    "Platform": "ST",
    "Timestamp": 1696326386000
  },
  {
    "Name": "",
    "Discoverer": "Lunivore",
    "Glyphs": "506CA11117FF",
    "Platform": "ST",
    "Timestamp": 1696326396000
  },
  {
    "Name": "",
    "Discoverer": "Lunivore",
    "Glyphs": "506CA11117FF",
    "Platform": "ST",
    "Timestamp": 1696326404000
  },
  {
    "Name": "",
    "Discoverer": "Lunivore",
    "Glyphs": "506CA11117FF",
    "Platform": "ST",
    "Timestamp": 1696326414000
  },
  {
    "Name": "",
    "Discoverer": "Lunivore",
    "Glyphs": "506CA11117FF",
    "Platform": "ST",
    "Timestamp": 1696326419000
  },
  {
    "Name": "",
    "Discoverer": "Lunivore",
    "Glyphs": "506CA11117FF",
    "Platform": "ST",
    "Timestamp": 1696326428000
  },
  {
    "Name": "",
    "Discoverer": "Lunivore",
    "Glyphs": "506CA11117FF",
    "Platform": "ST",
    "Timestamp": 1696326436000
  },
  {
    "Name": "",
    "Discoverer": "Lunivore",
    "Glyphs": "506CA11117FF",
    "Platform": "ST",
    "Timestamp": 1696692077000
  },
  {
    "Name": "",
    "Discoverer": "Lunivore",
    "Glyphs": "506CA11117FF",
    "Platform": "ST",
    "Timestamp": 1696753068000
  },
  {
    "Name": "",
    "Discoverer": "YucaFrita",
    "Glyphs": "5072A11117FF",
    "Platform": "ST",
    "Timestamp": 1711055745000
  },
  {
    "Name": "",
    "Discoverer": "YucaFrita",
    "Glyphs": "5072A11117FF",
    "Platform": "ST",
    "Timestamp": 1711055750000
  },
  {
    "Name": "",
    "Discoverer": "YucaFrita",
    "Glyphs": "5072A11117FF",
    "Platform": "ST",
    "Timestamp": 1711055759000
  },
  {
    "Name": "",
    "Discoverer": "YucaFrita",
    "Glyphs": "5072A11117FF",
    "Platform": "ST",
    "Timestamp": 1711055765000
  },
  {
    "Name": "",
    "Discoverer": "YucaFrita",
    "Glyphs": "5072A11117FF",
    "Platform": "ST",
    "Timestamp": 1711055771000
  },
  {
    "Name": "",
    "Discoverer": "YucaFrita",
    "Glyphs": "5072A11117FF",
    "Platform": "ST",
    "Timestamp": 1711055780000
  },
  {
    "Name": "",
    "Discoverer": "YucaFrita",
    "Glyphs": "5072A11117FF",
    "Platform": "ST",
    "Timestamp": 1711055791000
  },
  {
    "Name": "",
    "Discoverer": "Binder198",
    "Glyphs": "50DBA11117FF",
    "Platform": "ST",
    "Timestamp": 1700090977000
  },
  {
    "Name": "",
    "Discoverer": "Lunivore",
    "Glyphs": "50ECA11117FF",
    "Platform": "ST",
    "Timestamp": 1696864002000
  },
  {
    "Name": "",
    "Discoverer": "Lunivore",
    "Glyphs": "50ECA11117FF",
    "Platform": "ST",
    "Timestamp": 1696864010000
  },
  {
    "Name": "",
    "Discoverer": "Lunivore",
    "Glyphs": "50ECA11117FF",
    "Platform": "ST",
    "Timestamp": 1696864037000
  },
  {
    "Name": "",
    "Discoverer": "Lunivore",
    "Glyphs": "50ECA11117FF",
    "Platform": "ST",
    "Timestamp": 1696864058000
  },
  {
    "Name": "",
    "Discoverer": "Lunivore",
    "Glyphs": "50ECA11117FF",
    "Platform": "ST",
    "Timestamp": 1696864064000
  },
  {
    "Name": "",
    "Discoverer": "Lunivore",
    "Glyphs": "50ECA11117FF",
    "Platform": "ST",
    "Timestamp": 1696864073000
  },
  {
    "Name": "",
    "Discoverer": "Lunivore",
    "Glyphs": "50ECA11117FF",
    "Platform": "ST",
    "Timestamp": 1696864081000
  },
  {
    "Name": "",
    "Discoverer": "Lunivore",
    "Glyphs": "50ECA11117FF",
    "Platform": "ST",
    "Timestamp": 1696864088000
  },
  {
    "Name": "",
    "Discoverer": "Lunivore",
    "Glyphs": "50ECA11117FF",
    "Platform": "ST",
    "Timestamp": 1696864115000
  },
  {
    "Name": "",
    "Discoverer": "Lunivore",
    "Glyphs": "50ECA11117FF",
    "Platform": "ST",
    "Timestamp": 1696864132000
  },
  {
    "Name": "",
    "Discoverer": "Lunivore",
    "Glyphs": "50ECA11117FF",
    "Platform": "ST",
    "Timestamp": 1696864137000
  },
  {
    "Name": "",
    "Discoverer": "Lunivore",
    "Glyphs": "50ECA11117FF",
    "Platform": "ST",
    "Timestamp": 1696864153000
  },
  {
    "Name": "",
    "Discoverer": "Lunivore",
    "Glyphs": "50ECA11117FF",
    "Platform": "ST",
    "Timestamp": 1696864159000
  },
  {
    "Name": "",
    "Discoverer": "Lunivore",
    "Glyphs": "50ECA11117FF",
    "Platform": "ST",
    "Timestamp": 1696864165000
  },
  {
    "Name": "",
    "Discoverer": "Lunivore",
    "Glyphs": "50ECA11117FF",
    "Platform": "ST",
    "Timestamp": 1696864171000
  },
  {
    "Name": "",
    "Discoverer": "Lunivore",
    "Glyphs": "512BA11117FF",
    "Platform": "ST",
    "Timestamp": 1696771010000
  },
  {
    "Name": "",
    "Discoverer": "Lunivore",
    "Glyphs": "512BA11117FF",
    "Platform": "ST",
    "Timestamp": 1696771018000
  },
  {
    "Name": "",
    "Discoverer": "Lunivore",
    "Glyphs": "514FA11117FF",
    "Platform": "ST",
    "Timestamp": 1696182067000
  },
  {
    "Name": "",
    "Discoverer": "Lunivore",
    "Glyphs": "514FA11117FF",
    "Platform": "ST",
    "Timestamp": 1696182079000
  },
  {
    "Name": "",
    "Discoverer": "Lunivore",
    "Glyphs": "514FA11117FF",
    "Platform": "ST",
    "Timestamp": 1696182126000
  },
  {
    "Name": "",
    "Discoverer": "Lunivore",
    "Glyphs": "514FA11117FF",
    "Platform": "ST",
    "Timestamp": 1696182167000
  },
  {
    "Name": "",
    "Discoverer": "Lunivore",
    "Glyphs": "514FA11117FF",
    "Platform": "ST",
    "Timestamp": 1696182183000
  },
  {
    "Name": "",
    "Discoverer": "YucaFrita",
    "Glyphs": "6001A11117FF",
    "Platform": "ST",
    "Timestamp": 1695936012000
  },
  {
    "Name": "",
    "Discoverer": "YucaFrita",
    "Glyphs": "6001A11117FF",
    "Platform": "ST",
    "Timestamp": 1695936029000
  },
  {
    "Name": "",
    "Discoverer": "YucaFrita",
    "Glyphs": "6001A11117FF",
    "Platform": "ST",
    "Timestamp": 1695936057000
  },
  {
    "Name": "",
    "Discoverer": "YucaFrita",
    "Glyphs": "6001A11117FF",
    "Platform": "ST",
    "Timestamp": 1695936067000
  },
  {
    "Name": "",
    "Discoverer": "YucaFrita",
    "Glyphs": "6001A11117FF",
    "Platform": "ST",
    "Timestamp": 1695936091000
  },
  {
    "Name": "",
    "Discoverer": "YucaFrita",
    "Glyphs": "6001A11117FF",
    "Platform": "ST",
    "Timestamp": 1695936102000
  },
  {
    "Name": "",
    "Discoverer": "YucaFrita",
    "Glyphs": "6001A11117FF",
    "Platform": "ST",
    "Timestamp": 1695936107000
  },
  {
    "Name": "",
    "Discoverer": "LordDraCool241",
    "Glyphs": "601EA11117FF",
    "Platform": "XB",
    "Timestamp": 1712305383000
  },
  {
    "Name": "",
    "Discoverer": "LordDraCool241",
    "Glyphs": "601EA11117FF",
    "Platform": "XB",
    "Timestamp": 1712305389000
  },
  {
    "Name": "",
    "Discoverer": "LordDraCool241",
    "Glyphs": "601EA11117FF",
    "Platform": "XB",
    "Timestamp": 1712305398000
  },
  {
    "Name": "",
    "Discoverer": "LordDraCool241",
    "Glyphs": "601EA11117FF",
    "Platform": "XB",
    "Timestamp": 1712305404000
  },
  {
    "Name": "",
    "Discoverer": "YucaFrita",
    "Glyphs": "6027A11117FF",
    "Platform": "ST",
    "Timestamp": 1711291295000
  },
  {
    "Name": "",
    "Discoverer": "YucaFrita",
    "Glyphs": "6027A11117FF",
    "Platform": "ST",
    "Timestamp": 1711291303000
  },
  {
    "Name": "",
    "Discoverer": "YucaFrita",
    "Glyphs": "6027A11117FF",
    "Platform": "ST",
    "Timestamp": 1711291310000
  },
  {
    "Name": "",
    "Discoverer": "YucaFrita",
    "Glyphs": "6027A11117FF",
    "Platform": "ST",
    "Timestamp": 1711291319000
  },
  {
    "Name": "",
    "Discoverer": "YucaFrita",
    "Glyphs": "6027A11117FF",
    "Platform": "ST",
    "Timestamp": 1711291325000
  },
  {
    "Name": "",
    "Discoverer": "YucaFrita",
    "Glyphs": "6027A11117FF",
    "Platform": "ST",
    "Timestamp": 1711291332000
  },
  {
    "Name": "",
    "Discoverer": "YucaFrita",
    "Glyphs": "6027A11117FF",
    "Platform": "ST",
    "Timestamp": 1711291340000
  },
  {
    "Name": "",
    "Discoverer": "YucaFrita",
    "Glyphs": "6027A11117FF",
    "Platform": "ST",
    "Timestamp": 1711291345000
  },
  {
    "Name": "",
    "Discoverer": "YucaFrita",
    "Glyphs": "6027A11117FF",
    "Platform": "ST",
    "Timestamp": 1711291354000
  },
  {
    "Name": "",
    "Discoverer": "YucaFrita",
    "Glyphs": "6027A11117FF",
    "Platform": "ST",
    "Timestamp": 1711291359000
  },
  {
    "Name": "",
    "Discoverer": "Lunivore",
    "Glyphs": "6043A11117FF",
    "Platform": "ST",
    "Timestamp": 1703258801000
  },
  {
    "Name": "",
    "Discoverer": "Lunivore",
    "Glyphs": "6043A11117FF",
    "Platform": "ST",
    "Timestamp": 1703258823000
  },
  {
    "Name": "",
    "Discoverer": "Lunivore",
    "Glyphs": "6043A11117FF",
    "Platform": "ST",
    "Timestamp": 1703258833000
  },
  {
    "Name": "",
    "Discoverer": "Lunivore",
    "Glyphs": "6043A11117FF",
    "Platform": "ST",
    "Timestamp": 1703258838000
  },
  {
    "Name": "",
    "Discoverer": "Lunivore",
    "Glyphs": "6043A11117FF",
    "Platform": "ST",
    "Timestamp": 1703258843000
  },
  {
    "Name": "",
    "Discoverer": "Lunivore",
    "Glyphs": "6043A11117FF",
    "Platform": "ST",
    "Timestamp": 1703258881000
  },
  {
    "Name": "",
    "Discoverer": "Lunivore",
    "Glyphs": "6043A11117FF",
    "Platform": "ST",
    "Timestamp": 1703259839000
  },
  {
    "Name": "",
    "Discoverer": "Lunivore",
    "Glyphs": "6043A11117FF",
    "Platform": "ST",
    "Timestamp": 1703259855000
  },
  {
    "Name": "",
    "Discoverer": "Lunivore",
    "Glyphs": "6043A11117FF",
    "Platform": "ST",
    "Timestamp": 1703259867000
  },
  {
    "Name": "",
    "Discoverer": "Lunivore",
    "Glyphs": "6062A11117FF",
    "Platform": "ST",
    "Timestamp": 1696853837000
  },
  {
    "Name": "",
    "Discoverer": "Lunivore",
    "Glyphs": "6062A11117FF",
    "Platform": "ST",
    "Timestamp": 1696853846000
  },
  {
    "Name": "",
    "Discoverer": "Lunivore",
    "Glyphs": "6062A11117FF",
    "Platform": "ST",
    "Timestamp": 1696853854000
  },
  {
    "Name": "",
    "Discoverer": "Lunivore",
    "Glyphs": "6062A11117FF",
    "Platform": "ST",
    "Timestamp": 1696853867000
  },
  {
    "Name": "",
    "Discoverer": "Lunivore",
    "Glyphs": "6062A11117FF",
    "Platform": "ST",
    "Timestamp": 1696853901000
  },
  {
    "Name": "",
    "Discoverer": "Lunivore",
    "Glyphs": "6062A11117FF",
    "Platform": "ST",
    "Timestamp": 1696853910000
  },
  {
    "Name": "",
    "Discoverer": "Lunivore",
    "Glyphs": "6062A11117FF",
    "Platform": "ST",
    "Timestamp": 1696853934000
  },
  {
    "Name": "",
    "Discoverer": "Lunivore",
    "Glyphs": "6062A11117FF",
    "Platform": "ST",
    "Timestamp": 1696853975000
  },
  {
    "Name": "",
    "Discoverer": "Lunivore",
    "Glyphs": "606CA11117FF",
    "Platform": "ST",
    "Timestamp": 1696752915000
  },
  {
    "Name": "",
    "Discoverer": "Lunivore",
    "Glyphs": "606CA11117FF",
    "Platform": "ST",
    "Timestamp": 1696752940000
  },
  {
    "Name": "",
    "Discoverer": "Lunivore",
    "Glyphs": "606CA11117FF",
    "Platform": "ST",
    "Timestamp": 1696752950000
  },
  {
    "Name": "",
    "Discoverer": "Lunivore",
    "Glyphs": "606CA11117FF",
    "Platform": "ST",
    "Timestamp": 1696752956000
  },
  {
    "Name": "",
    "Discoverer": "Lunivore",
    "Glyphs": "606CA11117FF",
    "Platform": "ST",
    "Timestamp": 1696752963000
  },
  {
    "Name": "",
    "Discoverer": "Lunivore",
    "Glyphs": "606CA11117FF",
    "Platform": "ST",
    "Timestamp": 1696752982000
  },
  {
    "Name": "",
    "Discoverer": "Lunivore",
    "Glyphs": "606CA11117FF",
    "Platform": "ST",
    "Timestamp": 1696752988000
  },
  {
    "Name": "",
    "Discoverer": "Lunivore",
    "Glyphs": "606CA11117FF",
    "Platform": "ST",
    "Timestamp": 1696752996000
  },
  {
    "Name": "",
    "Discoverer": "Lunivore",
    "Glyphs": "606CA11117FF",
    "Platform": "ST",
    "Timestamp": 1696753007000
  },
  {
    "Name": "",
    "Discoverer": "YucaFrita",
    "Glyphs": "6072A11117FF",
    "Platform": "ST",
    "Timestamp": 1711131223000
  },
  {
    "Name": "",
    "Discoverer": "YucaFrita",
    "Glyphs": "6072A11117FF",
    "Platform": "ST",
    "Timestamp": 1711131232000
  },
  {
    "Name": "",
    "Discoverer": "YucaFrita",
    "Glyphs": "6072A11117FF",
    "Platform": "ST",
    "Timestamp": 1711131238000
  },
  {
    "Name": "",
    "Discoverer": "YucaFrita",
    "Glyphs": "6072A11117FF",
    "Platform": "ST",
    "Timestamp": 1711131247000
  },
  {
    "Name": "",
    "Discoverer": "YucaFrita",
    "Glyphs": "6072A11117FF",
    "Platform": "ST",
    "Timestamp": 1711131254000
  },
  {
    "Name": "",
    "Discoverer": "YucaFrita",
    "Glyphs": "6072A11117FF",
    "Platform": "ST",
    "Timestamp": 1711131263000
  },
  {
    "Name": "",
    "Discoverer": "YucaFrita",
    "Glyphs": "6072A11117FF",
    "Platform": "ST",
    "Timestamp": 1711131273000
  },
  {
    "Name": "",
    "Discoverer": "Lunivore",
    "Glyphs": "60ECA11117FF",
    "Platform": "ST",
    "Timestamp": 1696860525000
  },
  {
    "Name": "",
    "Discoverer": "Lunivore",
    "Glyphs": "60ECA11117FF",
    "Platform": "ST",
    "Timestamp": 1696860532000
  },
  {
    "Name": "",
    "Discoverer": "Lunivore",
    "Glyphs": "60ECA11117FF",
    "Platform": "ST",
    "Timestamp": 1696860541000
  },
  {
    "Name": "",
    "Discoverer": "Lunivore",
    "Glyphs": "60ECA11117FF",
    "Platform": "ST",
    "Timestamp": 1696860558000
  },
  {
    "Name": "",
    "Discoverer": "Lunivore",
    "Glyphs": "60ECA11117FF",
    "Platform": "ST",
    "Timestamp": 1696860572000
  },
  {
    "Name": "",
    "Discoverer": "Lunivore",
    "Glyphs": "60ECA11117FF",
    "Platform": "ST",
    "Timestamp": 1696860649000
  },
  {
    "Name": "",
    "Discoverer": "Lunivore",
    "Glyphs": "60ECA11117FF",
    "Platform": "ST",
    "Timestamp": 1696860679000
  },
  {
    "Name": "",
    "Discoverer": "Lunivore",
    "Glyphs": "60ECA11117FF",
    "Platform": "ST",
    "Timestamp": 1696860704000
  },
  {
    "Name": "",
    "Discoverer": "Lunivore",
    "Glyphs": "60ECA11117FF",
    "Platform": "ST",
    "Timestamp": 1696860710000
  },
  {
    "Name": "",
    "Discoverer": "Lunivore",
    "Glyphs": "60ECA11117FF",
    "Platform": "ST",
    "Timestamp": 1696860726000
  },
  {
    "Name": "",
    "Discoverer": "Lunivore",
    "Glyphs": "60ECA11117FF",
    "Platform": "ST",
    "Timestamp": 1696860757000
  },
  {
    "Name": "",
    "Discoverer": "Lunivore",
    "Glyphs": "60ECA11117FF",
    "Platform": "ST",
    "Timestamp": 1696860772000
  },
  {
    "Name": "",
    "Discoverer": "Lunivore",
    "Glyphs": "60ECA11117FF",
    "Platform": "ST",
    "Timestamp": 1696860804000
  },
  {
    "Name": "",
    "Discoverer": "Lunivore",
    "Glyphs": "60ECA11117FF",
    "Platform": "ST",
    "Timestamp": 1696860818000
  },
  {
    "Name": "",
    "Discoverer": "Lunivore",
    "Glyphs": "614FA11117FF",
    "Platform": "ST",
    "Timestamp": 1696181888000
  }
]